<mods xmlns="http://www.loc.gov/mods/v3" xmlns:xsi="http://www.w3.org/2001/XMLSchema-instance" xmlns:xlink="http://www.w3.org/1999/xlink" xsi:schemaLocation="http://www.loc.gov/mods/v3 http://www.loc.gov/standards/mods/v3/mods-3-3.xsd" version="3.3" ID="P0b002ee183eb593e">
<name type="corporate">
 <namePart>United States Government Printing Office</namePart>
 <role>
  <roleTerm type="text" authority="marcrelator">printer</roleTerm>
  <roleTerm type="code" authority="marcrelator">prt</roleTerm>
</role>
 <role>
  <roleTerm type="text" authority="marcrelator">distributor</roleTerm>
  <roleTerm type="code" authority="marcrelator">dst</roleTerm>
</role>
</name>
<name type="corporate">
 <namePart>United States</namePart>
 <namePart>Congress</namePart>
 <namePart>House of Representatives</namePart>
 <role>
  <roleTerm type="text" authority="marcrelator">author</roleTerm>
  <roleTerm type="code" authority="marcrelator">aut</roleTerm>
</role>
 <description>Government Organization</description>
</name>
<typeOfResource>text</typeOfResource>
<genre authority="marcgt">government publication</genre>
<language>
 <languageTerm authority="iso639-2b" type="code">eng</languageTerm>
</language>
<extension>
 <collectionCode>BILLS</collectionCode>
 <searchTitle>To amend title 18, United States Code, to prohibit taking minors across State lines in circumvention of laws requiring the involvement of parents in abortion decisions.;
   		Child Interstate Abortion Notification Act;H.R. 732 (IH)</searchTitle>
 <category>Bills and Statutes</category>
 <waisDatabaseName>113_cong_bills</waisDatabaseName>
 <branch>legislative</branch>
 <dateIngested>2013-03-19</dateIngested>
</extension>
<titleInfo>
 <title>To amend title 18, United States Code, to prohibit taking minors across State lines in circumvention of laws requiring the involvement of parents in abortion decisions.</title>
</titleInfo>
<titleInfo type="alternative">
 <title>Child Interstate Abortion Notification Act</title>
</titleInfo>
<titleInfo type="alternative">
 <title>H.R. 732 (IH)</title>
</titleInfo>
<originInfo>
 <publisher>U.S. Government Printing Office</publisher>
 <dateIssued encoding="w3cdtf">2013-02-14</dateIssued>
 <issuance>monographic</issuance>
</originInfo>
<physicalDescription>
 <note type="source content type">deposited</note>
 <digitalOrigin>born digital</digitalOrigin>
 <extent>12 p.</extent>
</physicalDescription>
<classification authority="sudocs">Y 1.6:</classification>
<classification authority="sudocs">Y 1.4/6:</classification>
<identifier type="local">P0b002ee183eb593e</identifier>
<identifier type="uri">http://www.gpo.gov/fdsys/pkg/BILLS-113hr732ih</identifier>
<identifier type="preferred citation">H.R. 732</identifier>
<identifier type="stock number">021-610-00252-9</identifier>
<identifier type="Parent ILS system id">000501532</identifier>
<identifier type="Child ILS system id">000325573</identifier>
<identifier type="Parent ILS title">Congressional bills</identifier>
<identifier type="Child ILS title">House bills</identifier>
<identifier type="former package identifier">f:h732_ih.txt</identifier>
<location xmlns:exslt="http://exslt.org/common">
 <url access="object in context" displayLabel="Content Detail">http://www.gpo.gov/fdsys/pkg/BILLS-113hr732ih/content-detail.html</url>
 <url access="raw object" displayLabel="HTML rendition">http://www.gpo.gov/fdsys/pkg/BILLS-113hr732ih/html/BILLS-113hr732ih.htm</url>
 <url access="raw object" displayLabel="PDF rendition">http://www.gpo.gov/fdsys/pkg/BILLS-113hr732ih/pdf/BILLS-113hr732ih.pdf</url>
 <url access="raw object" displayLabel="XML rendition">http://www.gpo.gov/fdsys/pkg/BILLS-113hr732ih/xml/BILLS-113hr732ih.xml</url>
</location>
<accessCondition type="GPO scope determination">fdlp</accessCondition>
<recordInfo>
 <recordContentSource authority="marcorg">DGPO</recordContentSource>
 <recordCreationDate encoding="w3cdtf">2013-03-19</recordCreationDate>
 <recordChangeDate encoding="w3cdtf">2014-05-06</recordChangeDate>
 <recordIdentifier source="DGPO">BILLS-113hr732ih</recordIdentifier>
 <recordOrigin>machine generated</recordOrigin>
 <languageOfCataloging>
  <languageTerm authority="iso639-2b" type="code">eng</languageTerm>
</languageOfCataloging>
</recordInfo>
<name type="personal">
 <namePart>Ileana Ros-Lehtinen</namePart>
 <affiliation>United States House of Representatives</affiliation>
 <role>
  <roleTerm type="text" authority="marcrelator">sponsor</roleTerm>
  <roleTerm type="code" authority="marcrelator">spn</roleTerm>
</role>
 <description>United States Congress Member</description>
</name>
<name type="personal">
 <namePart>Diane Black</namePart>
 <affiliation>United States House of Representatives</affiliation>
 <role>
  <roleTerm type="text">cosponsor</roleTerm>
</role>
 <description>United States Congress Member</description>
</name>
<name type="personal">
 <namePart>Charles W. Boustany Jr.</namePart>
 <affiliation>United States House of Representatives</affiliation>
 <role>
  <roleTerm type="text">cosponsor</roleTerm>
</role>
 <description>United States Congress Member</description>
</name>
<name type="personal">
 <namePart>Kevin Brady</namePart>
 <affiliation>United States House of Representatives</affiliation>
 <role>
  <roleTerm type="text">cosponsor</roleTerm>
</role>
 <description>United States Congress Member</description>
</name>
<name type="personal">
 <namePart>Trent Franks</namePart>
 <affiliation>United States House of Representatives</affiliation>
 <role>
  <roleTerm type="text">cosponsor</roleTerm>
</role>
 <description>United States Congress Member</description>
</name>
<name type="personal">
 <namePart>Walter B. Jones Jr.</namePart>
 <affiliation>United States House of Representatives</affiliation>
 <role>
  <roleTerm type="text">cosponsor</roleTerm>
</role>
 <description>United States Congress Member</description>
</name>
<name type="personal">
 <namePart>Scott DesJarlais</namePart>
 <affiliation>United States House of Representatives</affiliation>
 <role>
  <roleTerm type="text">cosponsor</roleTerm>
</role>
 <description>United States Congress Member</description>
</name>
<name type="personal">
 <namePart>Ander Crenshaw</namePart>
 <affiliation>United States House of Representatives</affiliation>
 <role>
  <roleTerm type="text">cosponsor</roleTerm>
</role>
 <description>United States Congress Member</description>
</name>
<name type="personal">
 <namePart>Daniel Lipinski</namePart>
 <affiliation>United States House of Representatives</affiliation>
 <role>
  <roleTerm type="text">cosponsor</roleTerm>
</role>
 <description>United States Congress Member</description>
</name>
<name type="personal">
 <namePart>Kenny Marchant</namePart>
 <affiliation>United States House of Representatives</affiliation>
 <role>
  <roleTerm type="text">cosponsor</roleTerm>
</role>
 <description>United States Congress Member</description>
</name>
<name type="personal">
 <namePart>Steve King</namePart>
 <affiliation>United States House of Representatives</affiliation>
 <role>
  <roleTerm type="text">cosponsor</roleTerm>
</role>
 <description>United States Congress Member</description>
</name>
<name type="personal">
 <namePart>H. Morgan Griffith</namePart>
 <affiliation>United States House of Representatives</affiliation>
 <role>
  <roleTerm type="text">cosponsor</roleTerm>
</role>
 <description>United States Congress Member</description>
</name>
<name type="personal">
 <namePart>Randy Neugebauer</namePart>
 <affiliation>United States House of Representatives</affiliation>
 <role>
  <roleTerm type="text">cosponsor</roleTerm>
</role>
 <description>United States Congress Member</description>
</name>
<name type="personal">
 <namePart>Steve Chabot</namePart>
 <affiliation>United States House of Representatives</affiliation>
 <role>
  <roleTerm type="text">cosponsor</roleTerm>
</role>
 <description>United States Congress Member</description>
</name>
<name type="personal">
 <namePart>Tom Cole</namePart>
 <affiliation>United States House of Representatives</affiliation>
 <role>
  <roleTerm type="text">cosponsor</roleTerm>
</role>
 <description>United States Congress Member</description>
</name>
<name type="personal">
 <namePart>Ralph M. Hall</namePart>
 <affiliation>United States House of Representatives</affiliation>
 <role>
  <roleTerm type="text">cosponsor</roleTerm>
</role>
 <description>United States Congress Member</description>
</name>
<name type="personal">
 <namePart>Scott Garrett</namePart>
 <affiliation>United States House of Representatives</affiliation>
 <role>
  <roleTerm type="text">cosponsor</roleTerm>
</role>
 <description>United States Congress Member</description>
</name>
<name type="personal">
 <namePart>John L. Mica</namePart>
 <affiliation>United States House of Representatives</affiliation>
 <role>
  <roleTerm type="text">cosponsor</roleTerm>
</role>
 <description>United States Congress Member</description>
</name>
<name type="personal">
 <namePart>Christopher H. Smith</namePart>
 <affiliation>United States House of Representatives</affiliation>
 <role>
  <roleTerm type="text">cosponsor</roleTerm>
</role>
 <description>United States Congress Member</description>
</name>
<name type="personal">
 <namePart>Stephen Lee Fincher</namePart>
 <affiliation>United States House of Representatives</affiliation>
 <role>
  <roleTerm type="text">cosponsor</roleTerm>
</role>
 <description>United States Congress Member</description>
</name>
<name type="personal">
 <namePart>Mike Pompeo</namePart>
 <affiliation>United States House of Representatives</affiliation>
 <role>
  <roleTerm type="text">cosponsor</roleTerm>
</role>
 <description>United States Congress Member</description>
</name>
<name type="personal">
 <namePart>Robert J. Wittman</namePart>
 <affiliation>United States House of Representatives</affiliation>
 <role>
  <roleTerm type="text">cosponsor</roleTerm>
</role>
 <description>United States Congress Member</description>
</name>
<name type="personal">
 <namePart>Ted Poe</namePart>
 <affiliation>United States House of Representatives</affiliation>
 <role>
  <roleTerm type="text">cosponsor</roleTerm>
</role>
 <description>United States Congress Member</description>
</name>
<name type="personal">
 <namePart>Mario Diaz-Balart</namePart>
 <affiliation>United States House of Representatives</affiliation>
 <role>
  <roleTerm type="text">cosponsor</roleTerm>
</role>
 <description>United States Congress Member</description>
</name>
<name type="personal">
 <namePart>Tim Griffin</namePart>
 <affiliation>United States House of Representatives</affiliation>
 <role>
  <roleTerm type="text">cosponsor</roleTerm>
</role>
 <description>United States Congress Member</description>
</name>
<name type="personal">
 <namePart>Steve Stivers</namePart>
 <affiliation>United States House of Representatives</affiliation>
 <role>
  <roleTerm type="text">cosponsor</roleTerm>
</role>
 <description>United States Congress Member</description>
</name>
<name type="personal">
 <namePart>John R. Carter</namePart>
 <affiliation>United States House of Representatives</affiliation>
 <role>
  <roleTerm type="text">cosponsor</roleTerm>
</role>
 <description>United States Congress Member</description>
</name>
<name type="personal">
 <namePart>Rodney Davis</namePart>
 <affiliation>United States House of Representatives</affiliation>
 <role>
  <roleTerm type="text">cosponsor</roleTerm>
</role>
 <description>United States Congress Member</description>
</name>
<name type="personal">
 <namePart>Vicky Hartzler</namePart>
 <affiliation>United States House of Representatives</affiliation>
 <role>
  <roleTerm type="text">cosponsor</roleTerm>
</role>
 <description>United States Congress Member</description>
</name>
<name type="personal">
 <namePart>Alan Nunnelee</namePart>
 <affiliation>United States House of Representatives</affiliation>
 <role>
  <roleTerm type="text">cosponsor</roleTerm>
</role>
 <description>United States Congress Member</description>
</name>
<name type="personal">
 <namePart>Tim Walberg</namePart>
 <affiliation>United States House of Representatives</affiliation>
 <role>
  <roleTerm type="text">cosponsor</roleTerm>
</role>
 <description>United States Congress Member</description>
</name>
<name type="personal">
 <namePart>Reid J. Ribble</namePart>
 <affiliation>United States House of Representatives</affiliation>
 <role>
  <roleTerm type="text">cosponsor</roleTerm>
</role>
 <description>United States Congress Member</description>
</name>
<name type="personal">
 <namePart>Mick Mulvaney</namePart>
 <affiliation>United States House of Representatives</affiliation>
 <role>
  <roleTerm type="text">cosponsor</roleTerm>
</role>
 <description>United States Congress Member</description>
</name>
<name type="personal">
 <namePart>Doug Lamborn</namePart>
 <affiliation>United States House of Representatives</affiliation>
 <role>
  <roleTerm type="text">cosponsor</roleTerm>
</role>
 <description>United States Congress Member</description>
</name>
<name type="personal">
 <namePart>Dan Benishek</namePart>
 <affiliation>United States House of Representatives</affiliation>
 <role>
  <roleTerm type="text">cosponsor</roleTerm>
</role>
 <description>United States Congress Member</description>
</name>
<name type="personal">
 <namePart>John Fleming</namePart>
 <affiliation>United States House of Representatives</affiliation>
 <role>
  <roleTerm type="text">cosponsor</roleTerm>
</role>
 <description>United States Congress Member</description>
</name>
<name type="personal">
 <namePart>Ken Calvert</namePart>
 <affiliation>United States House of Representatives</affiliation>
 <role>
  <roleTerm type="text">cosponsor</roleTerm>
</role>
 <description>United States Congress Member</description>
</name>
<name type="personal">
 <namePart>Mr. Kelly</namePart>
 <affiliation>United States House of Representatives</affiliation>
 <role>
  <roleTerm type="text">cosponsor</roleTerm>
</role>
 <description>United States Congress Member</description>
</name>
<name type="personal">
 <namePart>Steven M. Palazzo</namePart>
 <affiliation>United States House of Representatives</affiliation>
 <role>
  <roleTerm type="text">cosponsor</roleTerm>
</role>
 <description>United States Congress Member</description>
</name>
<name type="personal">
 <namePart>Brad R. Wenstrup</namePart>
 <affiliation>United States House of Representatives</affiliation>
 <role>
  <roleTerm type="text">cosponsor</roleTerm>
</role>
 <description>United States Congress Member</description>
</name>
<name type="personal">
 <namePart>Randy Hultgren</namePart>
 <affiliation>United States House of Representatives</affiliation>
 <role>
  <roleTerm type="text">cosponsor</roleTerm>
</role>
 <description>United States Congress Member</description>
</name>
<name type="personal">
 <namePart>Jim Jordan</namePart>
 <affiliation>United States House of Representatives</affiliation>
 <role>
  <roleTerm type="text">cosponsor</roleTerm>
</role>
 <description>United States Congress Member</description>
</name>
<name type="personal">
 <namePart>Stevan Pearce</namePart>
 <affiliation>United States House of Representatives</affiliation>
 <role>
  <roleTerm type="text">cosponsor</roleTerm>
</role>
 <description>United States Congress Member</description>
</name>
<name type="personal">
 <namePart>Joe Wilson</namePart>
 <affiliation>United States House of Representatives</affiliation>
 <role>
  <roleTerm type="text">cosponsor</roleTerm>
</role>
 <description>United States Congress Member</description>
</name>
<name type="personal">
 <namePart>Brett Guthrie</namePart>
 <affiliation>United States House of Representatives</affiliation>
 <role>
  <roleTerm type="text">cosponsor</roleTerm>
</role>
 <description>United States Congress Member</description>
</name>
<name type="personal">
 <namePart>Lynn A. Westmoreland</namePart>
 <affiliation>United States House of Representatives</affiliation>
 <role>
  <roleTerm type="text">cosponsor</roleTerm>
</role>
 <description>United States Congress Member</description>
</name>
<name type="personal">
 <namePart>Tom McClintock</namePart>
 <affiliation>United States House of Representatives</affiliation>
 <role>
  <roleTerm type="text">cosponsor</roleTerm>
</role>
 <description>United States Congress Member</description>
</name>
<name type="personal">
 <namePart>Marsha Blackburn</namePart>
 <affiliation>United States House of Representatives</affiliation>
 <role>
  <roleTerm type="text">cosponsor</roleTerm>
</role>
 <description>United States Congress Member</description>
</name>
<name type="personal">
 <namePart>Tim Huelskamp</namePart>
 <affiliation>United States House of Representatives</affiliation>
 <role>
  <roleTerm type="text">cosponsor</roleTerm>
</role>
 <description>United States Congress Member</description>
</name>
<name type="personal">
 <namePart>K. Michael Conaway</namePart>
 <affiliation>United States House of Representatives</affiliation>
 <role>
  <roleTerm type="text">cosponsor</roleTerm>
</role>
 <description>United States Congress Member</description>
</name>
<name type="personal">
 <namePart>Lee Terry</namePart>
 <affiliation>United States House of Representatives</affiliation>
 <role>
  <roleTerm type="text">cosponsor</roleTerm>
</role>
 <description>United States Congress Member</description>
</name>
<name type="personal">
 <namePart>Jeff Miller</namePart>
 <affiliation>United States House of Representatives</affiliation>
 <role>
  <roleTerm type="text">cosponsor</roleTerm>
</role>
 <description>United States Congress Member</description>
</name>
<name type="personal">
 <namePart>Bill Shuster</namePart>
 <affiliation>United States House of Representatives</affiliation>
 <role>
  <roleTerm type="text">cosponsor</roleTerm>
</role>
 <description>United States Congress Member</description>
</name>
<name type="personal">
 <namePart>Gus M. Bilirakis</namePart>
 <affiliation>United States House of Representatives</affiliation>
 <role>
  <roleTerm type="text">cosponsor</roleTerm>
</role>
 <description>United States Congress Member</description>
</name>
<name type="personal">
 <namePart>Patrick J. Tiberi</namePart>
 <affiliation>United States House of Representatives</affiliation>
 <role>
  <roleTerm type="text">cosponsor</roleTerm>
</role>
 <description>United States Congress Member</description>
</name>
<name type="personal">
 <namePart>Bill Huizenga</namePart>
 <affiliation>United States House of Representatives</affiliation>
 <role>
  <roleTerm type="text">cosponsor</roleTerm>
</role>
 <description>United States Congress Member</description>
</name>
<name type="personal">
 <namePart>Harold Rogers</namePart>
 <affiliation>United States House of Representatives</affiliation>
 <role>
  <roleTerm type="text">cosponsor</roleTerm>
</role>
 <description>United States Congress Member</description>
</name>
<name type="personal">
 <namePart>Robert E. Latta</namePart>
 <affiliation>United States House of Representatives</affiliation>
 <role>
  <roleTerm type="text">cosponsor</roleTerm>
</role>
 <description>United States Congress Member</description>
</name>
<name type="personal">
 <namePart>Peter T. King</namePart>
 <affiliation>United States House of Representatives</affiliation>
 <role>
  <roleTerm type="text">cosponsor</roleTerm>
</role>
 <description>United States Congress Member</description>
</name>
<name type="personal">
 <namePart>Pete Olson</namePart>
 <affiliation>United States House of Representatives</affiliation>
 <role>
  <roleTerm type="text">cosponsor</roleTerm>
</role>
 <description>United States Congress Member</description>
</name>
<name type="personal">
 <namePart>Sam Graves</namePart>
 <affiliation>United States House of Representatives</affiliation>
 <role>
  <roleTerm type="text">cosponsor</roleTerm>
</role>
 <description>United States Congress Member</description>
</name>
<name type="personal">
 <namePart>Jeb Hensarling</namePart>
 <affiliation>United States House of Representatives</affiliation>
 <role>
  <roleTerm type="text">cosponsor</roleTerm>
</role>
 <description>United States Congress Member</description>
</name>
<name type="personal">
 <namePart>Nick J. Rahall II</namePart>
 <affiliation>United States House of Representatives</affiliation>
 <role>
  <roleTerm type="text">cosponsor</roleTerm>
</role>
 <description>United States Congress Member</description>
</name>
<name type="personal">
 <namePart>Michael R. Turner</namePart>
 <affiliation>United States House of Representatives</affiliation>
 <role>
  <roleTerm type="text">cosponsor</roleTerm>
</role>
 <description>United States Congress Member</description>
</name>
<name type="personal">
 <namePart>Michele Bachmann</namePart>
 <affiliation>United States House of Representatives</affiliation>
 <role>
  <roleTerm type="text">cosponsor</roleTerm>
</role>
 <description>United States Congress Member</description>
</name>
<name type="personal">
 <namePart>Rodney Alexander</namePart>
 <affiliation>United States House of Representatives</affiliation>
 <role>
  <roleTerm type="text">cosponsor</roleTerm>
</role>
 <description>United States Congress Member</description>
</name>
<name type="personal">
 <namePart>Tim Murphy</namePart>
 <affiliation>United States House of Representatives</affiliation>
 <role>
  <roleTerm type="text">cosponsor</roleTerm>
</role>
 <description>United States Congress Member</description>
</name>
<name type="personal">
 <namePart>Markwayne Mullin</namePart>
 <affiliation>United States House of Representatives</affiliation>
 <role>
  <roleTerm type="text">cosponsor</roleTerm>
</role>
 <description>United States Congress Member</description>
</name>
<name type="personal">
 <namePart>Steve Scalise</namePart>
 <affiliation>United States House of Representatives</affiliation>
 <role>
  <roleTerm type="text">cosponsor</roleTerm>
</role>
 <description>United States Congress Member</description>
</name>
<name type="corporate">
 <namePart>United States</namePart>
 <namePart>Congress</namePart>
 <namePart>House of Representatives</namePart>
 <namePart>Committee on the Judiciary</namePart>
 <role>
  <roleTerm type="text" authority="marcrelator">associated name</roleTerm>
  <roleTerm type="code" authority="marcrelator">asn</roleTerm>
</role>
</name>
<extension>
 <docClass>hr</docClass>
 <accessId>BILLS-113hr732ih</accessId>
 <congress>113</congress>
 <session>1</session>
 <originChamber>HOUSE</originChamber>
 <currentChamber>HOUSE</currentChamber>
 <billNumber>732</billNumber>
 <billVersion reprint="false">ih</billVersion>
 <fileSuffix>ih</fileSuffix>
 <shortTitle>Child Interstate Abortion Notification Act</shortTitle>
 <action date="2013-02-14">Ms. Ros-Lehtinen (for herself, Mrs. Black, Mr. Boustany, Mr. Brady of Texas, Mr. Franks of Arizona, Mr. Jones, Mr. DesJarlais, Mr. Crenshaw, Mr. Lipinski, Mr. Marchant, Mr. King of Iowa, Mr. Griffith of Virginia, Mr. Neugebauer, Mr. Chabot, Mr. Cole, Mr. Hall, Mr. Garrett, Mr. Mica, Mr. Smith of New Jersey, Mr. Fincher, Mr. Pompeo, Mr. Wittman, Mr. Poe of Texas, Mr. Diaz-Balart, Mr. Griffin of Arkansas, Mr. Stivers, Mr. Carter, Mr. Rodney Davis of Illinois, Mrs. Hartzler, Mr. Nunnelee, Mr. Walberg, Mr. Ribble, Mr. Mulvaney, Mr. Lamborn, Mr. Benishek, Mr. Fleming, Mr. Calvert, Mr. Kelly, Mr. Palazzo, Mr. Wenstrup, Mr. Hultgren, Mr. Jordan, Mr. Pearce, Mr. Wilson of South Carolina, Mr. Guthrie, Mr. Westmoreland, Mr. McClintock, Mrs. Blackburn, Mr. Huelskamp, Mr. Conaway, Mr. Terry, Mr. Miller of Florida, Mr. Shuster, Mr. Bilirakis, Mr. Tiberi, Mr. Huizenga of Michigan, Mr. Rogers of Kentucky, Mr. Latta, Mr. King of New York, Mr. Olson, Mr. Graves of Missouri, Mr. Hensarling, Mr. Rahall, Mr. Turner, Mrs. Bachmann, Mr. Alexander, Mr. Murphy of Pennsylvania, Mr. Mullin, and Mr. Scalise) introduced the following bill; which was referred to the Committee on the Judiciary</action>
 <congCommittee authorityId="hsju00" chamber="H" congress="113" type="S">
                      <name type="authority-standard">Committee on the Judiciary</name>
                      <name type="authority-short">Judiciary</name>
                </congCommittee>
 <congMember authorityId="985" bioGuideId="R000435" chamber="H" congress="113" gpoId="7890" party="R" role="SPONSOR" state="FL">
                      <name type="parsed">Ms. Ros-Lehtinen</name>
                      <name type="authority-fnf">Ileana Ros-Lehtinen</name>
                      <name type="authority-lnf">Ros-Lehtinen, Ileana</name>
                </congMember>
 <congMember authorityId="2063" bioGuideId="B001273" chamber="H" congress="113" gpoId="8153" party="R" role="COSPONSOR" state="TN">
                      <name type="parsed">Mrs. Black</name>
                      <name type="authority-fnf">Diane Black</name>
                      <name type="authority-lnf">Black, Diane</name>
                </congMember>
 <congMember authorityId="1787" bioGuideId="B001255" chamber="H" congress="113" gpoId="7965" party="R" role="COSPONSOR" state="LA">
                      <name type="parsed">Mr. Boustany</name>
                      <name type="authority-fnf">Charles W. Boustany Jr.</name>
                      <name type="authority-lnf">Boustany, Charles W., Jr.</name>
                      <name type="authority-other">Mr. Charles Boustany Jr.</name>
                </congMember>
 <congMember authorityId="1468" bioGuideId="B000755" chamber="H" congress="113" gpoId="8164" party="R" role="COSPONSOR" state="TX">
                      <name type="parsed">Mr. Brady of Texas</name>
                      <name type="authority-fnf">Kevin Brady</name>
                      <name type="authority-lnf">Brady, Kevin</name>
                </congMember>
 <congMember authorityId="1707" bioGuideId="F000448" chamber="H" congress="113" gpoId="7799" party="R" role="COSPONSOR" state="AZ">
                      <name type="parsed">Mr. Franks of Arizona</name>
                      <name type="authority-fnf">Trent Franks</name>
                      <name type="authority-lnf">Franks, Trent</name>
                </congMember>
 <congMember authorityId="612" bioGuideId="J000255" chamber="H" congress="113" gpoId="8026" party="R" role="COSPONSOR" state="NC">
                      <name type="parsed">Mr. Jones</name>
                      <name type="authority-fnf">Walter B. Jones Jr.</name>
                      <name type="authority-lnf">Jones, Walter B., Jr.</name>
                      <name type="authority-other">Walter Jones Jr.</name>
                </congMember>
 <congMember authorityId="2062" bioGuideId="D000616" chamber="H" congress="113" gpoId="8151" party="R" role="COSPONSOR" state="TN">
                      <name type="parsed">Mr. DesJarlais</name>
                      <name type="authority-fnf">Scott DesJarlais</name>
                      <name type="authority-lnf">DesJarlais, Scott</name>
                </congMember>
 <congMember authorityId="1643" bioGuideId="C001045" chamber="H" congress="113" gpoId="7876" party="R" role="COSPONSOR" state="FL">
                      <name type="parsed">Mr. Crenshaw</name>
                      <name type="authority-fnf">Ander Crenshaw</name>
                      <name type="authority-lnf">Crenshaw, Ander</name>
                </congMember>
 <congMember authorityId="1781" bioGuideId="L000563" chamber="H" congress="113" gpoId="7923" party="D" role="COSPONSOR" state="IL">
                      <name type="parsed">Mr. Lipinski</name>
                      <name type="authority-fnf">Daniel Lipinski</name>
                      <name type="authority-lnf">Lipinski, Daniel</name>
                      <name type="authority-other">Mr. Daniel William Lipinski</name>
                </congMember>
 <congMember authorityId="1806" bioGuideId="M001158" chamber="H" congress="113" gpoId="8180" party="R" role="COSPONSOR" state="TX">
                      <name type="parsed">Mr. Marchant</name>
                      <name type="authority-fnf">Kenny Marchant</name>
                      <name type="authority-lnf">Marchant, Kenny</name>
                </congMember>
 <congMember authorityId="1724" bioGuideId="K000362" chamber="H" congress="113" gpoId="7918" party="R" role="COSPONSOR" state="IA">
                      <name type="parsed">Mr. King of Iowa</name>
                      <name type="authority-fnf">Steve King</name>
                      <name type="authority-lnf">King, Steve</name>
                </congMember>
 <congMember authorityId="2070" bioGuideId="G000568" chamber="H" congress="113" gpoId="8200" party="R" role="COSPONSOR" state="VA">
                      <name type="parsed">Mr. Griffith of Virginia</name>
                      <name type="authority-fnf">H. Morgan Griffith</name>
                      <name type="authority-lnf">Griffith, H. Morgan</name>
                </congMember>
 <congMember authorityId="1758" bioGuideId="N000182" chamber="H" congress="113" gpoId="8175" party="R" role="COSPONSOR" state="TX">
                      <name type="parsed">Mr. Neugebauer</name>
                      <name type="authority-fnf">Randy Neugebauer</name>
                      <name type="authority-lnf">Neugebauer, Randy</name>
                </congMember>
 <congMember authorityId="186" bioGuideId="C000266" chamber="H" congress="113" gpoId="8091" party="R" role="COSPONSOR" state="OH">
                      <name type="parsed">Mr. Chabot</name>
                      <name type="authority-fnf">Steve Chabot</name>
                      <name type="authority-lnf">Chabot, Steve</name>
                </congMember>
 <congMember authorityId="1742" bioGuideId="C001053" chamber="H" congress="113" gpoId="8112" party="R" role="COSPONSOR" state="OK">
                      <name type="parsed">Mr. Cole</name>
                      <name type="authority-fnf">Tom Cole</name>
                      <name type="authority-lnf">Cole, Tom</name>
                </congMember>
 <congMember authorityId="484" bioGuideId="H000067" chamber="H" congress="113" gpoId="8160" party="R" role="COSPONSOR" state="TX">
                      <name type="parsed">Mr. Hall</name>
                      <name type="authority-fnf">Ralph M. Hall</name>
                      <name type="authority-lnf">Hall, Ralph M.</name>
                      <name type="authority-other">Ralph Hall</name>
                </congMember>
 <congMember authorityId="1737" bioGuideId="G000548" chamber="H" congress="113" gpoId="8047" party="R" role="COSPONSOR" state="NJ">
                      <name type="parsed">Mr. Garrett</name>
                      <name type="authority-fnf">Scott Garrett</name>
                      <name type="authority-lnf">Garrett, Scott</name>
                </congMember>
 <congMember authorityId="800" bioGuideId="M000689" chamber="H" congress="113" gpoId="7879" party="R" role="COSPONSOR" state="FL">
                      <name type="parsed">Mr. Mica</name>
                      <name type="authority-fnf">John L. Mica</name>
                      <name type="authority-lnf">Mica, John L.</name>
                      <name type="authority-other">John Mica</name>
                </congMember>
 <congMember authorityId="1071" bioGuideId="S000522" chamber="H" congress="113" gpoId="8046" party="R" role="COSPONSOR" state="NJ">
                      <name type="parsed">Mr. Smith of New Jersey</name>
                      <name type="authority-fnf">Christopher H. Smith</name>
                      <name type="authority-lnf">Smith, Christopher H.</name>
                      <name type="authority-other">Christopher Smith</name>
                </congMember>
 <congMember authorityId="2064" bioGuideId="F000458" chamber="H" congress="113" gpoId="8155" party="R" role="COSPONSOR" state="TN">
                      <name type="parsed">Mr. Fincher</name>
                      <name type="authority-fnf">Stephen Lee Fincher</name>
                      <name type="authority-lnf">Fincher, Stephen Lee</name>
                      <name type="authority-other">Stephen Fincher</name>
                </congMember>
 <congMember authorityId="2022" bioGuideId="P000602" chamber="H" congress="113" gpoId="7952" party="R" role="COSPONSOR" state="KS">
                      <name type="parsed">Mr. Pompeo</name>
                      <name type="authority-fnf">Mike Pompeo</name>
                      <name type="authority-lnf">Pompeo, Mike</name>
                </congMember>
 <congMember authorityId="1886" bioGuideId="W000804" chamber="H" congress="113" gpoId="8192" party="R" role="COSPONSOR" state="VA">
                      <name type="parsed">Mr. Wittman</name>
                      <name type="authority-fnf">Robert J. Wittman</name>
                      <name type="authority-lnf">Wittman, Robert J.</name>
                      <name type="authority-other">Mr. Robert Wittman</name>
                </congMember>
 <congMember authorityId="1802" bioGuideId="P000592" chamber="H" congress="113" gpoId="8158" party="R" role="COSPONSOR" state="TX">
                      <name type="parsed">Mr. Poe of Texas</name>
                      <name type="authority-fnf">Ted Poe</name>
                      <name type="authority-lnf">Poe, Ted</name>
                </congMember>
 <congMember authorityId="1717" bioGuideId="D000600" chamber="H" congress="113" gpoId="7893" party="R" role="COSPONSOR" state="FL">
                      <name type="parsed">Mr. Diaz-Balart</name>
                      <name type="authority-fnf">Mario Diaz-Balart</name>
                      <name type="authority-lnf">Diaz-Balart, Mario</name>
                </congMember>
 <congMember authorityId="1990" bioGuideId="G000567" chamber="H" congress="113" gpoId="7794" party="R" role="COSPONSOR" state="AR">
                      <name type="parsed">Mr. Griffin of Arkansas</name>
                      <name type="authority-fnf">Tim Griffin</name>
                      <name type="authority-lnf">Griffin, Tim</name>
                </congMember>
 <congMember authorityId="2047" bioGuideId="S001187" chamber="H" congress="113" gpoId="8105" party="R" role="COSPONSOR" state="OH">
                      <name type="parsed">Mr. Stivers</name>
                      <name type="authority-fnf">Steve Stivers</name>
                      <name type="authority-lnf">Stivers, Steve</name>
                </congMember>
 <congMember authorityId="1752" bioGuideId="C001051" chamber="H" congress="113" gpoId="8187" party="R" role="COSPONSOR" state="TX">
                      <name type="parsed">Mr. Carter</name>
                      <name type="authority-fnf">John R. Carter</name>
                      <name type="authority-lnf">Carter, John R.</name>
                      <name type="authority-other">Mr. John Carter</name>
                </congMember>
 <congMember authorityId="2126" bioGuideId="D000619" chamber="H" congress="113" party="R" role="COSPONSOR" state="IL">
                      <name type="parsed">Mr. Rodney Davis of Illinois</name>
                      <name type="authority-fnf">Rodney Davis</name>
                      <name type="authority-lnf">Davis, Rodney</name>
                </congMember>
 <congMember authorityId="2032" bioGuideId="H001053" chamber="H" congress="113" gpoId="8012" party="R" role="COSPONSOR" state="MO">
                      <name type="parsed">Mrs. Hartzler</name>
                      <name type="authority-fnf">Vicky Hartzler</name>
                      <name type="authority-lnf">Hartzler, Vicky</name>
                </congMember>
 <congMember authorityId="2034" bioGuideId="N000186" chamber="H" congress="113" gpoId="8019" party="R" role="COSPONSOR" state="MS">
                      <name type="parsed">Mr. Nunnelee</name>
                      <name type="authority-fnf">Alan Nunnelee</name>
                      <name type="authority-lnf">Nunnelee, Alan</name>
                </congMember>
 <congMember authorityId="1855" bioGuideId="W000798" chamber="H" congress="113" gpoId="7992" party="R" role="COSPONSOR" state="MI">
                      <name type="parsed">Mr. Walberg</name>
                      <name type="authority-fnf">Tim Walberg</name>
                      <name type="authority-lnf">Walberg, Tim</name>
                      <name type="authority-other">Mr. Timothy Walberg</name>
                </congMember>
 <congMember authorityId="2073" bioGuideId="R000587" chamber="H" congress="113" gpoId="8221" party="R" role="COSPONSOR" state="WI">
                      <name type="parsed">Mr. Ribble</name>
                      <name type="authority-fnf">Reid J. Ribble</name>
                      <name type="authority-lnf">Ribble, Reid J.</name>
                      <name type="authority-other">Reid Ribble</name>
                </congMember>
 <congMember authorityId="2059" bioGuideId="M001182" chamber="H" congress="113" gpoId="8145" party="R" role="COSPONSOR" state="SC">
                      <name type="parsed">Mr. Mulvaney</name>
                      <name type="authority-fnf">Mick Mulvaney</name>
                      <name type="authority-lnf">Mulvaney, Mick</name>
                </congMember>
 <congMember authorityId="1834" bioGuideId="L000564" chamber="H" congress="113" gpoId="7863" party="R" role="COSPONSOR" state="CO">
                      <name type="parsed">Mr. Lamborn</name>
                      <name type="authority-fnf">Doug Lamborn</name>
                      <name type="authority-lnf">Lamborn, Doug</name>
                </congMember>
 <congMember authorityId="2027" bioGuideId="B001271" chamber="H" congress="113" gpoId="7986" party="R" role="COSPONSOR" state="MI">
                      <name type="parsed">Mr. Benishek</name>
                      <name type="authority-fnf">Dan Benishek</name>
                      <name type="authority-lnf">Benishek, Dan</name>
                </congMember>
 <congMember authorityId="1924" bioGuideId="F000456" chamber="H" congress="113" gpoId="7962" party="R" role="COSPONSOR" state="LA">
                      <name type="parsed">Mr. Fleming</name>
                      <name type="authority-fnf">John Fleming</name>
                      <name type="authority-lnf">Fleming, John</name>
                </congMember>
 <congMember authorityId="165" bioGuideId="C000059" chamber="H" congress="113" gpoId="7849" party="R" role="COSPONSOR" state="CA">
                      <name type="parsed">Mr. Calvert</name>
                      <name type="authority-fnf">Ken Calvert</name>
                      <name type="authority-lnf">Calvert, Ken</name>
                </congMember>
 <congMember chamber="H" congress="113" role="COSPONSOR">
                      <name type="parsed">Mr. Kelly</name>
                </congMember>
 <congMember authorityId="2035" bioGuideId="P000601" chamber="H" congress="113" gpoId="8022" party="R" role="COSPONSOR" state="MS">
                      <name type="parsed">Mr. Palazzo</name>
                      <name type="authority-fnf">Steven M. Palazzo</name>
                      <name type="authority-lnf">Palazzo, Steven M.</name>
                      <name type="authority-other">Steven Palazzo</name>
                </congMember>
 <congMember authorityId="2152" bioGuideId="W000815" chamber="H" congress="113" party="R" role="COSPONSOR" state="OH">
                      <name type="parsed">Mr. Wenstrup</name>
                      <name type="authority-fnf">Brad R. Wenstrup</name>
                      <name type="authority-lnf">Wenstrup, Brad R.</name>
                      <name type="authority-other">Brad Wenstrup</name>
                </congMember>
 <congMember authorityId="2015" bioGuideId="H001059" chamber="H" congress="113" gpoId="7934" party="R" role="COSPONSOR" state="IL">
                      <name type="parsed">Mr. Hultgren</name>
                      <name type="authority-fnf">Randy Hultgren</name>
                      <name type="authority-lnf">Hultgren, Randy</name>
                </congMember>
 <congMember authorityId="1868" bioGuideId="J000289" chamber="H" congress="113" gpoId="8094" party="R" role="COSPONSOR" state="OH">
                      <name type="parsed">Mr. Jordan</name>
                      <name type="authority-fnf">Jim Jordan</name>
                      <name type="authority-lnf">Jordan, Jim</name>
                </congMember>
 <congMember authorityId="1738" bioGuideId="P000588" chamber="H" congress="113" gpoId="8057" party="R" role="COSPONSOR" state="NM">
                      <name type="parsed">Mr. Pearce</name>
                      <name type="authority-fnf">Stevan Pearce</name>
                      <name type="authority-lnf">Pearce, Stevan</name>
                </congMember>
 <congMember authorityId="1688" bioGuideId="W000795" chamber="H" congress="113" gpoId="8142" party="R" role="COSPONSOR" state="SC">
                      <name type="parsed">Mr. Wilson of South Carolina</name>
                      <name type="authority-fnf">Joe Wilson</name>
                      <name type="authority-lnf">Wilson, Joe</name>
                </congMember>
 <congMember authorityId="1922" bioGuideId="G000558" chamber="H" congress="113" gpoId="7954" party="R" role="COSPONSOR" state="KY">
                      <name type="parsed">Mr. Guthrie</name>
                      <name type="authority-fnf">Brett Guthrie</name>
                      <name type="authority-lnf">Guthrie, Brett</name>
                </congMember>
 <congMember authorityId="1779" bioGuideId="W000796" chamber="H" congress="113" gpoId="7900" party="R" role="COSPONSOR" state="GA">
                      <name type="parsed">Mr. Westmoreland</name>
                      <name type="authority-fnf">Lynn A. Westmoreland</name>
                      <name type="authority-lnf">Westmoreland, Lynn A.</name>
                      <name type="authority-other">Mr. Lynn Westmoreland</name>
                </congMember>
 <congMember authorityId="1908" bioGuideId="M001177" chamber="H" congress="113" gpoId="7809" party="R" role="COSPONSOR" state="CA">
                      <name type="parsed">Mr. McClintock</name>
                      <name type="authority-fnf">Tom McClintock</name>
                      <name type="authority-lnf">McClintock, Tom</name>
                </congMember>
 <congMember authorityId="1748" bioGuideId="B001243" chamber="H" congress="113" gpoId="8154" party="R" role="COSPONSOR" state="TN">
                      <name type="parsed">Mrs. Blackburn</name>
                      <name type="authority-fnf">Marsha Blackburn</name>
                      <name type="authority-lnf">Blackburn, Marsha</name>
                </congMember>
 <congMember authorityId="2020" bioGuideId="H001057" chamber="H" congress="113" gpoId="7949" party="R" role="COSPONSOR" state="KS">
                      <name type="parsed">Mr. Huelskamp</name>
                      <name type="authority-fnf">Tim Huelskamp</name>
                      <name type="authority-lnf">Huelskamp, Tim</name>
                </congMember>
 <congMember authorityId="1805" bioGuideId="C001062" chamber="H" congress="113" gpoId="8167" party="R" role="COSPONSOR" state="TX">
                      <name type="parsed">Mr. Conaway</name>
                      <name type="authority-fnf">K. Michael Conaway</name>
                      <name type="authority-lnf">Conaway, K. Michael</name>
                </congMember>
 <congMember authorityId="1566" bioGuideId="T000459" chamber="H" congress="113" gpoId="8039" party="R" role="COSPONSOR" state="NE">
                      <name type="parsed">Mr. Terry</name>
                      <name type="authority-fnf">Lee Terry</name>
                      <name type="authority-lnf">Terry, Lee</name>
                </congMember>
 <congMember authorityId="1685" bioGuideId="M001144" chamber="H" congress="113" gpoId="7873" party="R" role="COSPONSOR" state="FL">
                      <name type="parsed">Mr. Miller of Florida</name>
                      <name type="authority-fnf">Jeff Miller</name>
                      <name type="authority-lnf">Miller, Jeff</name>
                </congMember>
 <congMember authorityId="1681" bioGuideId="S001154" chamber="H" congress="113" gpoId="8127" party="R" role="COSPONSOR" state="PA">
                      <name type="parsed">Mr. Shuster</name>
                      <name type="authority-fnf">Bill Shuster</name>
                      <name type="authority-lnf">Shuster, Bill</name>
                </congMember>
 <congMember authorityId="1838" bioGuideId="B001257" chamber="H" congress="113" gpoId="7881" party="R" role="COSPONSOR" state="FL">
                      <name type="parsed">Mr. Bilirakis</name>
                      <name type="authority-fnf">Gus M. Bilirakis</name>
                      <name type="authority-lnf">Bilirakis, Gus M.</name>
                      <name type="authority-other">Mr. Gus Bilirakis</name>
                </congMember>
 <congMember authorityId="1664" bioGuideId="T000462" chamber="H" congress="113" gpoId="8102" party="R" role="COSPONSOR" state="OH">
                      <name type="parsed">Mr. Tiberi</name>
                      <name type="authority-fnf">Patrick J. Tiberi</name>
                      <name type="authority-lnf">Tiberi, Patrick J.</name>
                      <name type="authority-other">Patrick Tiberi</name>
                </congMember>
 <congMember authorityId="2028" bioGuideId="H001058" chamber="H" congress="113" gpoId="7987" party="R" role="COSPONSOR" state="MI">
                      <name type="parsed">Mr. Huizenga of Michigan</name>
                      <name type="authority-fnf">Bill Huizenga</name>
                      <name type="authority-lnf">Huizenga, Bill</name>
                </congMember>
 <congMember authorityId="977" bioGuideId="R000395" chamber="H" congress="113" gpoId="7957" party="R" role="COSPONSOR" state="KY">
                      <name type="parsed">Mr. Rogers of Kentucky</name>
                      <name type="authority-fnf">Harold Rogers</name>
                      <name type="authority-lnf">Rogers, Harold</name>
                </congMember>
 <congMember authorityId="1885" bioGuideId="L000566" chamber="H" congress="113" gpoId="8095" party="R" role="COSPONSOR" state="OH">
                      <name type="parsed">Mr. Latta</name>
                      <name type="authority-fnf">Robert E. Latta</name>
                      <name type="authority-lnf">Latta, Robert E.</name>
                      <name type="authority-other">Mr. Robert Latta</name>
                </congMember>
 <congMember authorityId="635" bioGuideId="K000210" chamber="H" congress="113" gpoId="8064" party="R" role="COSPONSOR" state="NY">
                      <name type="parsed">Mr. King of New York</name>
                      <name type="authority-fnf">Peter T. King</name>
                      <name type="authority-lnf">King, Peter T.</name>
                      <name type="authority-other">Peter King</name>
                </congMember>
 <congMember authorityId="1955" bioGuideId="O000168" chamber="H" congress="113" gpoId="8178" party="R" role="COSPONSOR" state="TX">
                      <name type="parsed">Mr. Olson</name>
                      <name type="authority-fnf">Pete Olson</name>
                      <name type="authority-lnf">Olson, Pete</name>
                </congMember>
 <congMember authorityId="1656" bioGuideId="G000546" chamber="H" congress="113" gpoId="8014" party="R" role="COSPONSOR" state="MO">
                      <name type="parsed">Mr. Graves of Missouri</name>
                      <name type="authority-fnf">Sam Graves</name>
                      <name type="authority-lnf">Graves, Sam</name>
                </congMember>
 <congMember authorityId="1749" bioGuideId="H001036" chamber="H" congress="113" gpoId="8161" party="R" role="COSPONSOR" state="TX">
                      <name type="parsed">Mr. Hensarling</name>
                      <name type="authority-fnf">Jeb Hensarling</name>
                      <name type="authority-lnf">Hensarling, Jeb</name>
                </congMember>
 <congMember authorityId="940" bioGuideId="R000011" chamber="H" congress="113" gpoId="8224" party="D" role="COSPONSOR" state="WV">
                      <name type="parsed">Mr. Rahall</name>
                      <name type="authority-fnf">Nick J. Rahall II</name>
                      <name type="authority-lnf">Rahall, Nick J., II</name>
                      <name type="authority-other">Nick Rahall II</name>
                </congMember>
 <congMember authorityId="1741" bioGuideId="T000463" chamber="H" congress="113" gpoId="8093" party="R" role="COSPONSOR" state="OH">
                      <name type="parsed">Mr. Turner</name>
                      <name type="authority-fnf">Michael R. Turner</name>
                      <name type="authority-lnf">Turner, Michael R.</name>
                      <name type="authority-other">Mr. Michael Turner</name>
                </congMember>
 <congMember authorityId="1858" bioGuideId="B001256" chamber="H" congress="113" gpoId="8006" party="R" role="COSPONSOR" state="MN">
                      <name type="parsed">Mrs. Bachmann</name>
                      <name type="authority-fnf">Michele Bachmann</name>
                      <name type="authority-lnf">Bachmann, Michele</name>
                </congMember>
 <congMember authorityId="1727" bioGuideId="A000361" chamber="H" congress="113" gpoId="7963" party="R" role="COSPONSOR" state="LA">
                      <name type="parsed">Mr. Alexander</name>
                      <name type="authority-fnf">Rodney Alexander</name>
                      <name type="authority-lnf">Alexander, Rodney</name>
                      <name type="authority-other">Mr. Rodney Mckinnie Alexander</name>
                </congMember>
 <congMember authorityId="1744" bioGuideId="M001151" chamber="H" congress="113" gpoId="8136" party="R" role="COSPONSOR" state="PA">
                      <name type="parsed">Mr. Murphy of Pennsylvania</name>
                      <name type="authority-fnf">Tim Murphy</name>
                      <name type="authority-lnf">Murphy, Tim</name>
                </congMember>
 <congMember authorityId="2156" bioGuideId="M001190" chamber="H" congress="113" party="R" role="COSPONSOR" state="OK">
                      <name type="parsed">Mr. Mullin</name>
                      <name type="authority-fnf">Markwayne Mullin</name>
                      <name type="authority-lnf">Mullin, Markwayne</name>
                </congMember>
 <congMember authorityId="1892" bioGuideId="S001176" chamber="H" congress="113" gpoId="7959" party="R" role="COSPONSOR" state="LA">
                      <name type="parsed">Mr. Scalise</name>
                      <name type="authority-fnf">Steve Scalise</name>
                      <name type="authority-lnf">Scalise, Steve</name>
                </congMember>
 <isPrivate>false</isPrivate>
 <isAppropriation>false</isAppropriation>
</extension>
</mods>