{
  "actions": [
    {
      "acted_at": "2014-05-21", 
      "references": [
        {
          "reference": "CR E796", 
          "type": null
        }
      ], 
      "text": "Sponsor introductory remarks on measure.", 
      "type": "action"
    }, 
    {
      "acted_at": "2014-05-21", 
      "committees": [
        "HSFA"
      ], 
      "references": [], 
      "status": "REFERRED", 
      "text": "Referred to the House Committee on Foreign Affairs.", 
      "type": "referral"
    }
  ], 
  "amendments": [], 
  "bill_id": "hres592-113", 
  "bill_type": "hres", 
  "by_request": false, 
  "committees": [
    {
      "activity": [
        "referral"
      ], 
      "committee": "House Foreign Affairs", 
      "committee_id": "HSFA"
    }
  ], 
  "congress": "113", 
  "cosponsors": [
    {
      "district": "6", 
      "name": "Gerlach, Jim", 
      "sponsored_at": "2014-05-21", 
      "state": "PA", 
      "thomas_id": "01743", 
      "title": "Rep", 
      "withdrawn_at": null
    }, 
    {
      "district": "9", 
      "name": "Levin, Sander M.", 
      "sponsored_at": "2014-05-21", 
      "state": "MI", 
      "thomas_id": "00683", 
      "title": "Rep", 
      "withdrawn_at": null
    }, 
    {
      "district": "5", 
      "name": "Quigley, Mike", 
      "sponsored_at": "2014-05-21", 
      "state": "IL", 
      "thomas_id": "01967", 
      "title": "Rep", 
      "withdrawn_at": null
    }
  ], 
  "enacted_as": null, 
  "history": {
    "active": false, 
    "awaiting_signature": false, 
    "enacted": false, 
    "vetoed": false
  }, 
  "introduced_at": "2014-05-21", 
  "number": "592", 
  "official_title": "Calling for free and fair elections in Ukraine, and for other purposes.", 
  "popular_title": null, 
  "related_bills": [], 
  "short_title": null, 
  "sponsor": {
    "district": "9", 
    "name": "Kaptur, Marcy", 
    "state": "OH", 
    "thomas_id": "00616", 
    "title": "Rep", 
    "type": "person"
  }, 
  "status": "REFERRED", 
  "status_at": "2014-05-21", 
  "subjects": [
    "Elections, voting, political campaign regulation", 
    "Europe", 
    "Human rights", 
    "International affairs", 
    "Internet and video services", 
    "News media and reporting", 
    "Political movements and philosophies", 
    "Rule of law and government transparency", 
    "Russia", 
    "Sovereignty, recognition, national governance and status", 
    "Ukraine"
  ], 
  "subjects_top_term": "International affairs", 
  "summary": {
    "as": "Introduced", 
    "date": "2014-05-21", 
    "text": "Values the close relationship the United States has established with Ukraine since that country regained its independence in 1991.\n\nSupports freedom, human rights, civil liberties, and free elections in Ukraine.\n\n Supports the people of Ukraine in their peaceful calls for a representative and responsive democratic government.\n\n Condemns the interference of foreign agitators in pre-election activities that have disrupted security throughout Ukraine.\n\n Calls on the government of Ukraine to: (1) respect freedom of expression and association, and (2) allow international election monitors at the May 2014 election.\n\nUrges the President, the Secretary of State, and other world leaders to: (1) support the rights and freedoms of the people of Ukraine, (2) support policies and programs that preserve free and open access to the press and Internet in Ukraine, and (3) condemn elections that are not free and fair and do not meet international standards."
  }, 
  "titles": [
    {
      "as": "introduced", 
      "is_for_portion": false, 
      "title": "Calling for free and fair elections in Ukraine, and for other purposes.", 
      "type": "official"
    }
  ], 
  "updated_at": "2015-09-01T10:18:43-04:00", 
  "url": "http://thomas.loc.gov/cgi-bin/bdquery/z?d113:HE592:@@@L&summ2=m&"
}