{
  "actions": [
    {
      "acted_at": "2013-12-12", 
      "committees": [
        "HSIF"
      ], 
      "references": [], 
      "status": "REFERRED", 
      "text": "Referred to the Committee on Energy and Commerce, and in addition to the Committee on Ways and Means, for a period to be subsequently determined by the Speaker, in each case for consideration of such provisions as fall within the jurisdiction of the committee concerned.", 
      "type": "referral"
    }, 
    {
      "acted_at": "2013-12-12", 
      "committees": [
        "HSIF"
      ], 
      "references": [], 
      "text": "Referred to House Energy and Commerce", 
      "type": "referral"
    }, 
    {
      "acted_at": "2013-12-12", 
      "committees": [
        "HSWM"
      ], 
      "references": [], 
      "text": "Referred to House Ways and Means", 
      "type": "referral"
    }, 
    {
      "acted_at": "2013-12-13", 
      "in_committee": null, 
      "references": [], 
      "text": "Referred to the Subcommittee on Health.", 
      "type": "referral"
    }
  ], 
  "amendments": [], 
  "bill_id": "hr3769-113", 
  "bill_type": "hr", 
  "by_request": false, 
  "committees": [
    {
      "activity": [
        "referral"
      ], 
      "committee": "House Energy and Commerce", 
      "committee_id": "HSIF"
    }, 
    {
      "activity": [
        "referral"
      ], 
      "committee": "House Energy and Commerce", 
      "committee_id": "HSIF", 
      "subcommittee": "Subcommittee on Health", 
      "subcommittee_id": "14"
    }, 
    {
      "activity": [
        "referral"
      ], 
      "committee": "House Ways and Means", 
      "committee_id": "HSWM"
    }
  ], 
  "congress": "113", 
  "cosponsors": [
    {
      "district": "2", 
      "name": "Jenkins, Lynn", 
      "sponsored_at": "2013-12-12", 
      "state": "KS", 
      "thomas_id": "01921", 
      "title": "Rep", 
      "withdrawn_at": null
    }, 
    {
      "district": "3", 
      "name": "Jones, Walter B., Jr.", 
      "sponsored_at": "2014-03-24", 
      "state": "NC", 
      "thomas_id": "00612", 
      "title": "Rep", 
      "withdrawn_at": null
    }, 
    {
      "district": "3", 
      "name": "Latham, Tom", 
      "sponsored_at": "2014-03-12", 
      "state": "IA", 
      "thomas_id": "00666", 
      "title": "Rep", 
      "withdrawn_at": null
    }
  ], 
  "enacted_as": null, 
  "history": {
    "active": false, 
    "awaiting_signature": false, 
    "enacted": false, 
    "vetoed": false
  }, 
  "introduced_at": "2013-12-12", 
  "number": "3769", 
  "official_title": "To extend the nonenforcement instruction for the Medicare direct supervision requirement for therapeutic hospital outpatient services insofar as it applies to critical access hospitals and rural hospitals, to require a study of the impact on critical access hospitals and rural hospitals of a failure to extend such instruction, and for other purposes.", 
  "popular_title": null, 
  "related_bills": [], 
  "short_title": null, 
  "sponsor": {
    "district": "3", 
    "name": "Smith, Adrian", 
    "state": "NE", 
    "thomas_id": "01860", 
    "title": "Rep", 
    "type": "person"
  }, 
  "status": "REFERRED", 
  "status_at": "2013-12-12", 
  "subjects": [
    "Administrative law and regulatory procedures", 
    "Congressional oversight", 
    "Department of Health and Human Services", 
    "Government studies and investigations", 
    "Health", 
    "Health facilities and institutions", 
    "Home and outpatient care", 
    "Hospital care", 
    "Medicare", 
    "Rural conditions and development"
  ], 
  "subjects_top_term": "Health", 
  "summary": {
    "as": "Introduced", 
    "date": "2013-12-12", 
    "text": "Directs the Secretary of Health and Human Services (HHS), during a specified extension period, to extend the therapy supervision nonenforcement instruction (the enforcement instruction on supervision requirements for outpatient therapeutic services in critical access and small rural hospitals, as extended for calendar year 2013 by the Centers for Medicare & Medicaid Services).\n\nDirects the Secretary to study the impact (including the economic impact and the impact upon hospital staffing needs, if any) on critical access hospitals and small rural hospitals of not extending the therapy supervision nonenforcement instruction."
  }, 
  "titles": [
    {
      "as": "introduced", 
      "is_for_portion": false, 
      "title": "To extend the nonenforcement instruction for the Medicare direct supervision requirement for therapeutic hospital outpatient services insofar as it applies to critical access hospitals and rural hospitals, to require a study of the impact on critical access hospitals and rural hospitals of a failure to extend such instruction, and for other purposes.", 
      "type": "official"
    }
  ], 
  "updated_at": "2015-09-01T10:20:16-04:00", 
  "url": "http://thomas.loc.gov/cgi-bin/bdquery/z?d113:HR3769:@@@L&summ2=m&"
}