<mods xmlns="http://www.loc.gov/mods/v3" xmlns:xsi="http://www.w3.org/2001/XMLSchema-instance" xmlns:xlink="http://www.w3.org/1999/xlink" xsi:schemaLocation="http://www.loc.gov/mods/v3 http://www.loc.gov/standards/mods/v3/mods-3-3.xsd" version="3.3" ID="P0b002ee189abe858">
<name type="corporate">
 <namePart>United States Government Printing Office</namePart>
 <role>
  <roleTerm type="text" authority="marcrelator">printer</roleTerm>
  <roleTerm type="code" authority="marcrelator">prt</roleTerm>
</role>
 <role>
  <roleTerm type="text" authority="marcrelator">distributor</roleTerm>
  <roleTerm type="code" authority="marcrelator">dst</roleTerm>
</role>
</name>
<name type="corporate">
 <namePart>United States</namePart>
 <namePart>Congress</namePart>
 <namePart>House of Representatives</namePart>
 <role>
  <roleTerm type="text" authority="marcrelator">author</roleTerm>
  <roleTerm type="code" authority="marcrelator">aut</roleTerm>
</role>
 <description>Government Organization</description>
</name>
<typeOfResource>text</typeOfResource>
<genre authority="marcgt">government publication</genre>
<language>
 <languageTerm authority="iso639-2b" type="code">eng</languageTerm>
</language>
<extension>
 <collectionCode>BILLS</collectionCode>
 <searchTitle>To secure the border between the United States and Mexico.;
   		Safely Exacting Cautious Useful Rules for Immigration This Year (SECURITY) Act;H.R. 5316 (IH)</searchTitle>
 <category>Bills and Statutes</category>
 <waisDatabaseName>113_cong_bills</waisDatabaseName>
 <branch>legislative</branch>
 <dateIngested>2014-08-21</dateIngested>
</extension>
<titleInfo>
 <title>To secure the border between the United States and Mexico.</title>
</titleInfo>
<titleInfo type="alternative">
 <title>Safely Exacting Cautious Useful Rules for Immigration This Year (SECURITY) Act</title>
</titleInfo>
<titleInfo type="alternative">
 <title>H.R. 5316 (IH)</title>
</titleInfo>
<originInfo>
 <publisher>U.S. Government Printing Office</publisher>
 <dateIssued encoding="w3cdtf">2014-07-31</dateIssued>
 <issuance>monographic</issuance>
</originInfo>
<physicalDescription>
 <note type="source content type">deposited</note>
 <digitalOrigin>born digital</digitalOrigin>
 <extent>36 p.</extent>
</physicalDescription>
<classification authority="sudocs">Y 1.6:</classification>
<classification authority="sudocs">Y 1.4/6:</classification>
<identifier type="local">P0b002ee189abe858</identifier>
<identifier type="uri">http://www.gpo.gov/fdsys/pkg/BILLS-113hr5316ih</identifier>
<identifier type="preferred citation">H.R. 5316</identifier>
<identifier type="stock number">021-610-00252-9</identifier>
<identifier type="Parent ILS system id">000501532</identifier>
<identifier type="Child ILS system id">000325573</identifier>
<identifier type="Parent ILS title">Congressional bills</identifier>
<identifier type="Child ILS title">House bills</identifier>
<identifier type="former package identifier">f:h5316_ih.txt</identifier>
<location xmlns:exslt="http://exslt.org/common">
 <url access="object in context" displayLabel="Content Detail">http://www.gpo.gov/fdsys/pkg/BILLS-113hr5316ih/content-detail.html</url>
 <url access="raw object" displayLabel="HTML rendition">http://www.gpo.gov/fdsys/pkg/BILLS-113hr5316ih/html/BILLS-113hr5316ih.htm</url>
 <url access="raw object" displayLabel="PDF rendition">http://www.gpo.gov/fdsys/pkg/BILLS-113hr5316ih/pdf/BILLS-113hr5316ih.pdf</url>
 <url access="raw object" displayLabel="XML rendition">http://www.gpo.gov/fdsys/pkg/BILLS-113hr5316ih/xml/BILLS-113hr5316ih.xml</url>
</location>
<accessCondition type="GPO scope determination">fdlp</accessCondition>
<recordInfo>
 <recordContentSource authority="marcorg">DGPO</recordContentSource>
 <recordCreationDate encoding="w3cdtf">2014-08-21</recordCreationDate>
 <recordChangeDate encoding="w3cdtf">2014-08-21</recordChangeDate>
 <recordIdentifier source="DGPO">BILLS-113hr5316ih</recordIdentifier>
 <recordOrigin>machine generated</recordOrigin>
 <languageOfCataloging>
  <languageTerm authority="iso639-2b" type="code">eng</languageTerm>
</languageOfCataloging>
</recordInfo>
<name type="personal">
 <namePart>Steve Stockman</namePart>
 <affiliation>United States House of Representatives</affiliation>
 <role>
  <roleTerm type="text">cosponsor</roleTerm>
</role>
 <description>United States Congress Member</description>
</name>
<name type="corporate">
 <namePart>United States</namePart>
 <namePart>Congress</namePart>
 <namePart>House of Representatives</namePart>
 <namePart>Committee on Armed Services</namePart>
 <role>
  <roleTerm type="text" authority="marcrelator">associated name</roleTerm>
  <roleTerm type="code" authority="marcrelator">asn</roleTerm>
</role>
</name>
<name type="corporate">
 <namePart>United States</namePart>
 <namePart>Congress</namePart>
 <namePart>House of Representatives</namePart>
 <namePart>Committee on Foreign Affairs</namePart>
 <role>
  <roleTerm type="text" authority="marcrelator">associated name</roleTerm>
  <roleTerm type="code" authority="marcrelator">asn</roleTerm>
</role>
</name>
<name type="corporate">
 <namePart>United States</namePart>
 <namePart>Congress</namePart>
 <namePart>House of Representatives</namePart>
 <namePart>Committee on Homeland Security</namePart>
 <role>
  <roleTerm type="text" authority="marcrelator">associated name</roleTerm>
  <roleTerm type="code" authority="marcrelator">asn</roleTerm>
</role>
</name>
<name type="corporate">
 <namePart>United States</namePart>
 <namePart>Congress</namePart>
 <namePart>House of Representatives</namePart>
 <namePart>Committee on the Judiciary</namePart>
 <role>
  <roleTerm type="text" authority="marcrelator">associated name</roleTerm>
  <roleTerm type="code" authority="marcrelator">asn</roleTerm>
</role>
</name>
<name type="corporate">
 <namePart>United States</namePart>
 <namePart>Congress</namePart>
 <namePart>House of Representatives</namePart>
 <namePart>Committee on Ways and Means</namePart>
 <role>
  <roleTerm type="text" authority="marcrelator">associated name</roleTerm>
  <roleTerm type="code" authority="marcrelator">asn</roleTerm>
</role>
</name>
<relatedItem xmlns:exslt="http://exslt.org/common" type="isReferencedBy">
 <titleInfo>
  <title>United States Code</title>
  <partNumber>Title 8 Section 1101(a)</partNumber>
  <partNumber>Title 8 Section 1101et seq.</partNumber>
  <partNumber>Title 8 Section 1158(b)(2)(A)</partNumber>
  <partNumber>Title 8 Section 1182</partNumber>
  <partNumber>Title 8 Section 1182(a)(2)</partNumber>
  <partNumber>Title 8 Section 1226(c)(1)(D)</partNumber>
  <partNumber>Title 8 Section 1227(a)(2)</partNumber>
  <partNumber>Title 8 Section 1251(b)(3)(B)</partNumber>
  <partNumber>Title 8 Section 1253(d)</partNumber>
  <partNumber>Title 8 Section 1254a</partNumber>
  <partNumber>Title 8 Section 1641</partNumber>
</titleInfo>
 <identifier type="USC citation">8 U.S.C. 1101(a)</identifier>
 <identifier type="USC citation">8 U.S.C. 1101et seq.</identifier>
 <identifier type="USC citation">8 U.S.C. 1158(b)(2)(A)</identifier>
 <identifier type="USC citation">8 U.S.C. 1182</identifier>
 <identifier type="USC citation">8 U.S.C. 1182(a)(2)</identifier>
 <identifier type="USC citation">8 U.S.C. 1226(c)(1)(D)</identifier>
 <identifier type="USC citation">8 U.S.C. 1227(a)(2)</identifier>
 <identifier type="USC citation">8 U.S.C. 1251(b)(3)(B)</identifier>
 <identifier type="USC citation">8 U.S.C. 1253(d)</identifier>
 <identifier type="USC citation">8 U.S.C. 1254a</identifier>
 <identifier type="USC citation">8 U.S.C. 1641</identifier>
</relatedItem>
<relatedItem xmlns:exslt="http://exslt.org/common" type="isReferencedBy">
 <titleInfo>
  <title>United States Code</title>
  <partNumber>Title 16 Section 18</partNumber>
</titleInfo>
 <identifier type="USC citation">16 U.S.C. 18</identifier>
</relatedItem>
<relatedItem xmlns:exslt="http://exslt.org/common" type="isReferencedBy">
 <titleInfo>
  <title>United States Code</title>
  <partNumber>Title 18 Section 1028</partNumber>
  <partNumber>Title 18 Section 1029</partNumber>
  <partNumber>Title 18 Section 16</partNumber>
</titleInfo>
 <identifier type="USC citation">18 U.S.C. 1028</identifier>
 <identifier type="USC citation">18 U.S.C. 1029</identifier>
 <identifier type="USC citation">18 U.S.C. 16</identifier>
</relatedItem>
<relatedItem xmlns:exslt="http://exslt.org/common" type="isReferencedBy">
 <titleInfo>
  <title>United States Code</title>
  <partNumber>Title 21 Section 802</partNumber>
</titleInfo>
 <identifier type="USC citation">21 U.S.C. 802</identifier>
</relatedItem>
<relatedItem xmlns:exslt="http://exslt.org/common" type="isReferencedBy">
 <titleInfo>
  <title>United States Code</title>
  <partNumber>Title 32 Section 502(f)</partNumber>
</titleInfo>
 <identifier type="USC citation">32 U.S.C. 502(f)</identifier>
</relatedItem>
<relatedItem xmlns:exslt="http://exslt.org/common">
 <titleInfo>
  <title>United States Public Law 109-367</title>
</titleInfo>
 <identifier type="public law citation">Public Law 109-367</identifier>
</relatedItem>
<relatedItem xmlns:exslt="http://exslt.org/common">
 <titleInfo>
  <title>United States Public Law 110-161</title>
</titleInfo>
 <identifier type="public law citation">Public Law 110-161</identifier>
</relatedItem>
<relatedItem xmlns:exslt="http://exslt.org/common">
 <titleInfo>
  <title>United States Public Law 111-203</title>
</titleInfo>
 <identifier type="public law citation">Public Law 111-203</identifier>
</relatedItem>
<extension>
 <docClass>hr</docClass>
 <accessId>BILLS-113hr5316ih</accessId>
 <congress>113</congress>
 <session>2</session>
 <originChamber>HOUSE</originChamber>
 <currentChamber>HOUSE</currentChamber>
 <billNumber>5316</billNumber>
 <billVersion reprint="false">ih</billVersion>
 <fileSuffix>ih</fileSuffix>
 <shortTitle>Safely Exacting Cautious Useful Rules for Immigration This Year (SECURITY) Act</shortTitle>
 <action date="2014-07-31">Mr. Stockman introduced the following bill; which was referred to the Committee on the Judiciary, and in addition to the Committees on Homeland Security, Ways and Means, Armed Services, and Foreign Affairs, for a period to be subsequently determined by the Speaker, in each case for consideration of such provisions as fall within the jurisdiction of the committee concerned</action>
 <congCommittee authorityId="hsas00" chamber="H" congress="113" type="S">
                      <name type="authority-standard">Committee on Armed Services</name>
                      <name type="authority-short">Armed Services</name>
                </congCommittee>
 <congCommittee authorityId="hsfa00" chamber="H" congress="113" type="S">
                      <name type="authority-standard">Committee on Foreign Affairs</name>
                      <name type="authority-short">Foreign Affairs</name>
                </congCommittee>
 <congCommittee authorityId="hshm00" chamber="H" congress="113" type="S">
                      <name type="authority-standard">Committee on Homeland Security</name>
                      <name type="authority-short">Homeland Security</name>
                </congCommittee>
 <congCommittee authorityId="hsju00" chamber="H" congress="113" type="S">
                      <name type="authority-standard">Committee on the Judiciary</name>
                      <name type="authority-short">Judiciary</name>
                </congCommittee>
 <congCommittee authorityId="hswm00" chamber="H" congress="113" type="S">
                      <name type="authority-standard">Committee on Ways and Means</name>
                      <name type="authority-short">Ways and Means</name>
                </congCommittee>
 <congMember authorityId="1114" bioGuideId="S000937" chamber="H" congress="113" party="R" role="COSPONSOR" state="TX">
                      <name type="parsed">Mr. Stockman</name>
                      <name type="authority-fnf">Steve Stockman</name>
                      <name type="authority-lnf">Stockman, Steve</name>
                </congMember>
 <law congress="109" isPrivate="false" number="367"></law>
 <law congress="110" isPrivate="false" number="161"></law>
 <law congress="111" isPrivate="false" number="203"></law>
 <isPrivate>false</isPrivate>
 <isAppropriation>false</isAppropriation>
 <USCode title="8">
                      <section detail="(a)" number="1101"></section>
                      <section detail="et seq." number="1101"></section>
                      <section detail="(b)(2)(A)" number="1158"></section>
                      <section number="1182"></section>
                      <section detail="(a)(2)" number="1182"></section>
                      <section detail="(c)(1)(D)" number="1226"></section>
                      <section detail="(a)(2)" number="1227"></section>
                      <section detail="(b)(3)(B)" number="1251"></section>
                      <section detail="(d)" number="1253"></section>
                      <section number="1254a"></section>
                      <section number="1641"></section>
                </USCode>
 <USCode title="16">
                      <section number="18"></section>
                </USCode>
 <USCode title="18">
                      <section number="1028"></section>
                      <section number="1029"></section>
                      <section number="16"></section>
                </USCode>
 <USCode title="21">
                      <section number="802"></section>
                </USCode>
 <USCode title="32">
                      <section detail="(f)" number="502"></section>
                </USCode>
</extension>
</mods>