{
  "actions": [
    {
      "acted_at": "2013-11-19", 
      "committees": [
        "HSJU"
      ], 
      "references": [], 
      "status": "REFERRED", 
      "text": "Referred to the House Committee on the Judiciary.", 
      "type": "referral"
    }, 
    {
      "acted_at": "2014-01-09", 
      "committees": [
        "HSHM"
      ], 
      "in_committee": null, 
      "references": [], 
      "text": "Referred to the Subcommittee on Crime, Terrorism, Homeland Security, and Investigations.", 
      "type": "referral"
    }, 
    {
      "acted_at": "2014-04-29", 
      "committees": [
        "HSHM"
      ], 
      "in_committee": null, 
      "references": [], 
      "text": "Subcommittee on Crime, Terrorism, Homeland Security, and Investigations Discharged.", 
      "type": "action"
    }, 
    {
      "acted_at": "2014-04-30", 
      "in_committee": null, 
      "references": [], 
      "text": "Committee Consideration and Mark-up Session Held.", 
      "type": "action"
    }, 
    {
      "acted_at": "2014-04-30", 
      "in_committee": null, 
      "references": [], 
      "status": "REPORTED", 
      "text": "Ordered to be Reported (Amended) by Voice Vote.", 
      "type": "calendar"
    }, 
    {
      "acted_at": "2014-05-15T14:47:00-04:00", 
      "committees": [
        "HSJU"
      ], 
      "references": [], 
      "text": "Reported (Amended) by the Committee on Judiciary. H. Rept. 113-450.", 
      "type": "action"
    }, 
    {
      "acted_at": "2014-05-15T14:48:00-04:00", 
      "calendar": "Union", 
      "number": "332", 
      "references": [], 
      "text": "Placed on the Union Calendar, Calendar No. 332.", 
      "type": "calendar", 
      "under": null
    }, 
    {
      "acted_at": "2014-05-20T14:45:00-04:00", 
      "references": [], 
      "text": "Mr. Goodlatte moved to suspend the rules and pass the bill, as amended.", 
      "type": "action"
    }, 
    {
      "acted_at": "2014-05-20T14:46:00-04:00", 
      "references": [
        {
          "reference": "CR H4501-4509", 
          "type": "consideration"
        }
      ], 
      "text": "Considered under suspension of the rules.", 
      "type": "action"
    }, 
    {
      "acted_at": "2014-05-20T14:46:00-04:00", 
      "references": [], 
      "text": "DEBATE - The House proceeded with forty minutes of debate on H.R. 3530.", 
      "type": "action"
    }, 
    {
      "acted_at": "2014-05-20T15:23:00-04:00", 
      "references": [], 
      "text": "At the conclusion of debate, the Yeas and Nays were demanded and ordered. Pursuant to the provisions of clause 8, rule XX, the Chair announced that further proceedings on the motion would be postponed.", 
      "type": "action"
    }, 
    {
      "acted_at": "2014-05-20T17:59:00-04:00", 
      "references": [
        {
          "reference": "CR H4534-4535", 
          "type": "consideration"
        }
      ], 
      "text": "Considered as unfinished business.", 
      "type": "action"
    }, 
    {
      "acted_at": "2014-05-20T18:27:00-04:00", 
      "how": "roll", 
      "references": [
        {
          "reference": "CR H4501-4504", 
          "type": "text"
        }
      ], 
      "result": "pass", 
      "roll": "221", 
      "status": "PASS_OVER:HOUSE", 
      "suspension": true, 
      "text": "On motion to suspend the rules and pass the bill, as amended Agreed to by the Yeas and Nays: (2/3 required): 409 - 0 (Roll no. 221).", 
      "type": "vote", 
      "vote_type": "vote", 
      "where": "h"
    }, 
    {
      "acted_at": "2014-05-21", 
      "references": [], 
      "text": "Received in the Senate.", 
      "type": "action"
    }
  ], 
  "amendments": [], 
  "bill_id": "hr3530-113", 
  "bill_type": "hr", 
  "by_request": false, 
  "committees": [
    {
      "activity": [
        "referral", 
        "markup", 
        "reporting"
      ], 
      "committee": "House Judiciary", 
      "committee_id": "HSJU"
    }, 
    {
      "activity": [
        "referral", 
        "discharged"
      ], 
      "committee": "House Judiciary", 
      "committee_id": "HSJU", 
      "subcommittee": "Subcommittee on Crime, Terrorism, Homeland Security, and Investigations", 
      "subcommittee_id": "08"
    }
  ], 
  "congress": "113", 
  "cosponsors": [
    {
      "district": "6", 
      "name": "Bachmann, Michele", 
      "sponsored_at": "2014-05-08", 
      "state": "MN", 
      "thomas_id": "01858", 
      "title": "Rep", 
      "withdrawn_at": null
    }, 
    {
      "district": "37", 
      "name": "Bass, Karen", 
      "sponsored_at": "2014-03-12", 
      "state": "CA", 
      "thomas_id": "01996", 
      "title": "Rep", 
      "withdrawn_at": null
    }, 
    {
      "district": "6", 
      "name": "Black, Diane", 
      "sponsored_at": "2014-04-01", 
      "state": "TN", 
      "thomas_id": "02063", 
      "title": "Rep", 
      "withdrawn_at": null
    }, 
    {
      "district": "7", 
      "name": "Blackburn, Marsha", 
      "sponsored_at": "2014-02-05", 
      "state": "TN", 
      "thomas_id": "01748", 
      "title": "Rep", 
      "withdrawn_at": null
    }, 
    {
      "district": "3", 
      "name": "Blumenauer, Earl", 
      "sponsored_at": "2014-05-06", 
      "state": "OR", 
      "thomas_id": "00099", 
      "title": "Rep", 
      "withdrawn_at": null
    }, 
    {
      "district": "8", 
      "name": "Brady, Kevin", 
      "sponsored_at": "2014-02-05", 
      "state": "TX", 
      "thomas_id": "01468", 
      "title": "Rep", 
      "withdrawn_at": null
    }, 
    {
      "district": "5", 
      "name": "Brooks, Susan W.", 
      "sponsored_at": "2014-05-02", 
      "state": "IN", 
      "thomas_id": "02129", 
      "title": "Rep", 
      "withdrawn_at": null
    }, 
    {
      "district": "26", 
      "name": "Burgess, Michael C.", 
      "sponsored_at": "2014-02-05", 
      "state": "TX", 
      "thomas_id": "01751", 
      "title": "Rep", 
      "withdrawn_at": null
    }, 
    {
      "district": "17", 
      "name": "Bustos, Cheri", 
      "sponsored_at": "2014-05-06", 
      "state": "IL", 
      "thomas_id": "02127", 
      "title": "Rep", 
      "withdrawn_at": null
    }, 
    {
      "district": "29", 
      "name": "Cardenas, Tony", 
      "sponsored_at": "2013-12-10", 
      "state": "CA", 
      "thomas_id": "02107", 
      "title": "Rep", 
      "withdrawn_at": null
    }, 
    {
      "district": "31", 
      "name": "Carter, John R.", 
      "sponsored_at": "2014-03-06", 
      "state": "TX", 
      "thomas_id": "01752", 
      "title": "Rep", 
      "withdrawn_at": null
    }, 
    {
      "district": "17", 
      "name": "Cartwright, Matt", 
      "sponsored_at": "2014-01-29", 
      "state": "PA", 
      "thomas_id": "02159", 
      "title": "Rep", 
      "withdrawn_at": null
    }, 
    {
      "district": "3", 
      "name": "Chaffetz, Jason", 
      "sponsored_at": "2014-04-01", 
      "state": "UT", 
      "thomas_id": "01956", 
      "title": "Rep", 
      "withdrawn_at": null
    }, 
    {
      "district": "6", 
      "name": "Coble, Howard", 
      "sponsored_at": "2014-04-30", 
      "state": "NC", 
      "thomas_id": "00211", 
      "title": "Rep", 
      "withdrawn_at": null
    }, 
    {
      "district": "6", 
      "name": "Coffman, Mike", 
      "sponsored_at": "2014-04-08", 
      "state": "CO", 
      "thomas_id": "01912", 
      "title": "Rep", 
      "withdrawn_at": null
    }, 
    {
      "district": "9", 
      "name": "Collins, Doug", 
      "sponsored_at": "2014-04-30", 
      "state": "GA", 
      "thomas_id": "02121", 
      "title": "Rep", 
      "withdrawn_at": null
    }, 
    {
      "district": "11", 
      "name": "Conaway, K. Michael", 
      "sponsored_at": "2014-03-04", 
      "state": "TX", 
      "thomas_id": "01805", 
      "title": "Rep", 
      "withdrawn_at": null
    }, 
    {
      "district": "16", 
      "name": "Costa, Jim", 
      "sponsored_at": "2013-12-10", 
      "state": "CA", 
      "thomas_id": "01774", 
      "title": "Rep", 
      "withdrawn_at": null
    }, 
    {
      "district": "4", 
      "name": "Cotton, Tom", 
      "sponsored_at": "2014-04-30", 
      "state": "AR", 
      "thomas_id": "02098", 
      "title": "Rep", 
      "withdrawn_at": null
    }, 
    {
      "district": null, 
      "name": "Cramer, Kevin", 
      "sponsored_at": "2014-05-15", 
      "state": "ND", 
      "thomas_id": "02144", 
      "title": "Rep", 
      "withdrawn_at": null
    }, 
    {
      "district": "7", 
      "name": "Culberson, John Abney", 
      "sponsored_at": "2014-04-29", 
      "state": "TX", 
      "thomas_id": "01670", 
      "title": "Rep", 
      "withdrawn_at": null
    }, 
    {
      "district": null, 
      "name": "Daines, Steve", 
      "sponsored_at": "2014-02-05", 
      "state": "MT", 
      "thomas_id": "02138", 
      "title": "Rep", 
      "withdrawn_at": null
    }, 
    {
      "district": "13", 
      "name": "Davis, Rodney", 
      "sponsored_at": "2013-12-10", 
      "state": "IL", 
      "thomas_id": "02126", 
      "title": "Rep", 
      "withdrawn_at": null
    }, 
    {
      "district": "3", 
      "name": "DeLauro, Rosa L.", 
      "sponsored_at": "2014-04-04", 
      "state": "CT", 
      "thomas_id": "00281", 
      "title": "Rep", 
      "withdrawn_at": null
    }, 
    {
      "district": "1", 
      "name": "DelBene, Suzan K.", 
      "sponsored_at": "2014-01-15", 
      "state": "WA", 
      "thomas_id": "02096", 
      "title": "Rep", 
      "withdrawn_at": null
    }, 
    {
      "district": "6", 
      "name": "DeSantis, Ron", 
      "sponsored_at": "2014-04-30", 
      "state": "FL", 
      "thomas_id": "02116", 
      "title": "Rep", 
      "withdrawn_at": null
    }, 
    {
      "district": "21", 
      "name": "Deutch, Theodore E.", 
      "sponsored_at": "2014-01-17", 
      "state": "FL", 
      "thomas_id": "01976", 
      "title": "Rep", 
      "withdrawn_at": null
    }, 
    {
      "district": "25", 
      "name": "Diaz-Balart, Mario", 
      "sponsored_at": "2014-05-07", 
      "state": "FL", 
      "thomas_id": "01717", 
      "title": "Rep", 
      "withdrawn_at": null
    }, 
    {
      "district": "35", 
      "name": "Doggett, Lloyd", 
      "sponsored_at": "2014-02-03", 
      "state": "TX", 
      "thomas_id": "00303", 
      "title": "Rep", 
      "withdrawn_at": null
    }, 
    {
      "district": "3", 
      "name": "Duncan, Jeff", 
      "sponsored_at": "2014-02-05", 
      "state": "SC", 
      "thomas_id": "02057", 
      "title": "Rep", 
      "withdrawn_at": null
    }, 
    {
      "district": "5", 
      "name": "Esty, Elizabeth H.", 
      "sponsored_at": "2014-05-01", 
      "state": "CT", 
      "thomas_id": "02114", 
      "title": "Rep", 
      "withdrawn_at": null
    }, 
    {
      "district": "27", 
      "name": "Farenthold, Blake", 
      "sponsored_at": "2013-12-12", 
      "state": "TX", 
      "thomas_id": "02067", 
      "title": "Rep", 
      "withdrawn_at": null
    }, 
    {
      "district": "8", 
      "name": "Fincher, Stephen Lee", 
      "sponsored_at": "2014-02-05", 
      "state": "TN", 
      "thomas_id": "02064", 
      "title": "Rep", 
      "withdrawn_at": null
    }, 
    {
      "district": "8", 
      "name": "Fitzpatrick, Michael G.", 
      "sponsored_at": "2013-11-20", 
      "state": "PA", 
      "thomas_id": "01797", 
      "title": "Rep", 
      "withdrawn_at": null
    }, 
    {
      "district": "4", 
      "name": "Fleming, John", 
      "sponsored_at": "2014-02-05", 
      "state": "LA", 
      "thomas_id": "01924", 
      "title": "Rep", 
      "withdrawn_at": null
    }, 
    {
      "district": "17", 
      "name": "Flores, Bill", 
      "sponsored_at": "2014-02-05", 
      "state": "TX", 
      "thomas_id": "02065", 
      "title": "Rep", 
      "withdrawn_at": null
    }, 
    {
      "district": "22", 
      "name": "Frankel, Lois", 
      "sponsored_at": "2014-04-10", 
      "state": "FL", 
      "thomas_id": "02119", 
      "title": "Rep", 
      "withdrawn_at": null
    }, 
    {
      "district": "8", 
      "name": "Franks, Trent", 
      "sponsored_at": "2014-02-05", 
      "state": "AZ", 
      "thomas_id": "01707", 
      "title": "Rep", 
      "withdrawn_at": null
    }, 
    {
      "district": "11", 
      "name": "Frelinghuysen, Rodney P.", 
      "sponsored_at": "2014-05-08", 
      "state": "NJ", 
      "thomas_id": "00414", 
      "title": "Rep", 
      "withdrawn_at": null
    }, 
    {
      "district": "11", 
      "name": "Fudge, Marcia L.", 
      "sponsored_at": "2014-05-06", 
      "state": "OH", 
      "thomas_id": "01895", 
      "title": "Rep", 
      "withdrawn_at": null
    }, 
    {
      "district": "4", 
      "name": "Gosar, Paul A.", 
      "sponsored_at": "2014-05-09", 
      "state": "AZ", 
      "thomas_id": "01992", 
      "title": "Rep", 
      "withdrawn_at": null
    }, 
    {
      "district": "4", 
      "name": "Gowdy, Trey", 
      "sponsored_at": "2014-04-30", 
      "state": "SC", 
      "thomas_id": "02058", 
      "title": "Rep", 
      "withdrawn_at": null
    }, 
    {
      "district": "12", 
      "name": "Granger, Kay", 
      "sponsored_at": "2013-11-19", 
      "state": "TX", 
      "thomas_id": "01487", 
      "title": "Rep", 
      "withdrawn_at": null
    }, 
    {
      "district": "9", 
      "name": "Grayson, Alan", 
      "sponsored_at": "2014-05-02", 
      "state": "FL", 
      "thomas_id": "01914", 
      "title": "Rep", 
      "withdrawn_at": null
    }, 
    {
      "district": "4", 
      "name": "Gutierrez, Luis V.", 
      "sponsored_at": "2014-03-21", 
      "state": "IL", 
      "thomas_id": "00478", 
      "title": "Rep", 
      "withdrawn_at": null
    }, 
    {
      "district": "4", 
      "name": "Hall, Ralph M.", 
      "sponsored_at": "2013-11-21", 
      "state": "TX", 
      "thomas_id": "00484", 
      "title": "Rep", 
      "withdrawn_at": null
    }, 
    {
      "district": "1", 
      "name": "Harris, Andy", 
      "sponsored_at": "2014-02-05", 
      "state": "MD", 
      "thomas_id": "02026", 
      "title": "Rep", 
      "withdrawn_at": null
    }, 
    {
      "district": "4", 
      "name": "Hartzler, Vicky", 
      "sponsored_at": "2014-04-07", 
      "state": "MO", 
      "thomas_id": "02032", 
      "title": "Rep", 
      "withdrawn_at": null
    }, 
    {
      "district": "3", 
      "name": "Heck, Joseph J.", 
      "sponsored_at": "2014-04-30", 
      "state": "NV", 
      "thomas_id": "02040", 
      "title": "Rep", 
      "withdrawn_at": null
    }, 
    {
      "district": "3", 
      "name": "Herrera Beutler, Jaime", 
      "sponsored_at": "2014-04-29", 
      "state": "WA", 
      "thomas_id": "02071", 
      "title": "Rep", 
      "withdrawn_at": null
    }, 
    {
      "district": "17", 
      "name": "Honda, Michael M.", 
      "sponsored_at": "2014-05-06", 
      "state": "CA", 
      "thomas_id": "01634", 
      "title": "Rep", 
      "withdrawn_at": null
    }, 
    {
      "district": "8", 
      "name": "Hudson, Richard", 
      "sponsored_at": "2014-05-08", 
      "state": "NC", 
      "thomas_id": "02140", 
      "title": "Rep", 
      "withdrawn_at": null
    }, 
    {
      "district": "14", 
      "name": "Hultgren, Randy", 
      "sponsored_at": "2014-02-05", 
      "state": "IL", 
      "thomas_id": "02015", 
      "title": "Rep", 
      "withdrawn_at": null
    }, 
    {
      "district": "18", 
      "name": "Jackson Lee, Sheila", 
      "sponsored_at": "2014-04-29", 
      "state": "TX", 
      "thomas_id": "00588", 
      "title": "Rep", 
      "withdrawn_at": null
    }, 
    {
      "district": "6", 
      "name": "Johnson, Bill", 
      "sponsored_at": "2013-12-11", 
      "state": "OH", 
      "thomas_id": "02046", 
      "title": "Rep", 
      "withdrawn_at": null
    }, 
    {
      "district": "3", 
      "name": "Johnson, Sam", 
      "sponsored_at": "2014-04-02", 
      "state": "TX", 
      "thomas_id": "00603", 
      "title": "Rep", 
      "withdrawn_at": null
    }, 
    {
      "district": "13", 
      "name": "Jolly, David W.", 
      "sponsored_at": "2014-04-30", 
      "state": "FL", 
      "thomas_id": "02199", 
      "title": "Rep", 
      "withdrawn_at": null
    }, 
    {
      "district": "6", 
      "name": "Kilmer, Derek", 
      "sponsored_at": "2014-05-09", 
      "state": "WA", 
      "thomas_id": "02169", 
      "title": "Rep", 
      "withdrawn_at": null
    }, 
    {
      "district": "4", 
      "name": "King, Steve", 
      "sponsored_at": "2014-02-05", 
      "state": "IA", 
      "thomas_id": "01724", 
      "title": "Rep", 
      "withdrawn_at": null
    }, 
    {
      "district": "1", 
      "name": "Kirkpatrick, Ann", 
      "sponsored_at": "2014-04-30", 
      "state": "AZ", 
      "thomas_id": "01907", 
      "title": "Rep", 
      "withdrawn_at": null
    }, 
    {
      "district": "2", 
      "name": "Kline, John", 
      "sponsored_at": "2014-04-29", 
      "state": "MN", 
      "thomas_id": "01733", 
      "title": "Rep", 
      "withdrawn_at": null
    }, 
    {
      "district": "2", 
      "name": "Kuster, Ann M.", 
      "sponsored_at": "2014-04-29", 
      "state": "NH", 
      "thomas_id": "02145", 
      "title": "Rep", 
      "withdrawn_at": null
    }, 
    {
      "district": "1", 
      "name": "Labrador, Raul R.", 
      "sponsored_at": "2014-01-17", 
      "state": "ID", 
      "thomas_id": "02011", 
      "title": "Rep", 
      "withdrawn_at": null
    }, 
    {
      "district": "1", 
      "name": "LaMalfa, Doug", 
      "sponsored_at": "2014-02-05", 
      "state": "CA", 
      "thomas_id": "02100", 
      "title": "Rep", 
      "withdrawn_at": null
    }, 
    {
      "district": "5", 
      "name": "Lankford, James", 
      "sponsored_at": "2014-05-07", 
      "state": "OK", 
      "thomas_id": "02050", 
      "title": "Rep", 
      "withdrawn_at": null
    }, 
    {
      "district": "5", 
      "name": "Latta, Robert E.", 
      "sponsored_at": "2014-04-09", 
      "state": "OH", 
      "thomas_id": "01885", 
      "title": "Rep", 
      "withdrawn_at": null
    }, 
    {
      "district": "9", 
      "name": "Levin, Sander M.", 
      "sponsored_at": "2014-04-30", 
      "state": "MI", 
      "thomas_id": "00683", 
      "title": "Rep", 
      "withdrawn_at": null
    }, 
    {
      "district": "19", 
      "name": "Lofgren, Zoe", 
      "sponsored_at": "2014-05-01", 
      "state": "CA", 
      "thomas_id": "00701", 
      "title": "Rep", 
      "withdrawn_at": null
    }, 
    {
      "district": "47", 
      "name": "Lowenthal, Alan S.", 
      "sponsored_at": "2014-03-25", 
      "state": "CA", 
      "thomas_id": "02111", 
      "title": "Rep", 
      "withdrawn_at": null
    }, 
    {
      "district": null, 
      "name": "Lummis, Cynthia M.", 
      "sponsored_at": "2014-02-05", 
      "state": "WY", 
      "thomas_id": "01960", 
      "title": "Rep", 
      "withdrawn_at": null
    }, 
    {
      "district": "12", 
      "name": "Maloney, Carolyn B.", 
      "sponsored_at": "2013-11-19", 
      "state": "NY", 
      "thomas_id": "00729", 
      "title": "Rep", 
      "withdrawn_at": null
    }, 
    {
      "district": "10", 
      "name": "Marino, Tom", 
      "sponsored_at": "2014-04-30", 
      "state": "PA", 
      "thomas_id": "02053", 
      "title": "Rep", 
      "withdrawn_at": null
    }, 
    {
      "district": "10", 
      "name": "McCaul, Michael T.", 
      "sponsored_at": "2014-02-04", 
      "state": "TX", 
      "thomas_id": "01804", 
      "title": "Rep", 
      "withdrawn_at": null
    }, 
    {
      "district": "2", 
      "name": "McGovern, James P.", 
      "sponsored_at": "2014-02-27", 
      "state": "MA", 
      "thomas_id": "01504", 
      "title": "Rep", 
      "withdrawn_at": null
    }, 
    {
      "district": "7", 
      "name": "McIntyre, Mike", 
      "sponsored_at": "2014-04-29", 
      "state": "NC", 
      "thomas_id": "01505", 
      "title": "Rep", 
      "withdrawn_at": null
    }, 
    {
      "district": "5", 
      "name": "Meeks, Gregory W.", 
      "sponsored_at": "2013-12-05", 
      "state": "NY", 
      "thomas_id": "01506", 
      "title": "Rep", 
      "withdrawn_at": null
    }, 
    {
      "district": "10", 
      "name": "Miller, Candice S.", 
      "sponsored_at": "2013-11-19", 
      "state": "MI", 
      "thomas_id": "01731", 
      "title": "Rep", 
      "withdrawn_at": null
    }, 
    {
      "district": "8", 
      "name": "Moran, James P.", 
      "sponsored_at": "2013-12-05", 
      "state": "VA", 
      "thomas_id": "00832", 
      "title": "Rep", 
      "withdrawn_at": null
    }, 
    {
      "district": "5", 
      "name": "Mulvaney, Mick", 
      "sponsored_at": "2014-02-10", 
      "state": "SC", 
      "thomas_id": "02059", 
      "title": "Rep", 
      "withdrawn_at": null
    }, 
    {
      "district": "18", 
      "name": "Murphy, Patrick", 
      "sponsored_at": "2014-02-03", 
      "state": "FL", 
      "thomas_id": "02117", 
      "title": "Rep", 
      "withdrawn_at": null
    }, 
    {
      "district": "10", 
      "name": "Nadler, Jerrold", 
      "sponsored_at": "2014-04-30", 
      "state": "NY", 
      "thomas_id": "00850", 
      "title": "Rep", 
      "withdrawn_at": null
    }, 
    {
      "district": "32", 
      "name": "Napolitano, Grace F.", 
      "sponsored_at": "2014-04-30", 
      "state": "CA", 
      "thomas_id": "01602", 
      "title": "Rep", 
      "withdrawn_at": null
    }, 
    {
      "district": "19", 
      "name": "Neugebauer, Randy", 
      "sponsored_at": "2014-02-18", 
      "state": "TX", 
      "thomas_id": "01758", 
      "title": "Rep", 
      "withdrawn_at": null
    }, 
    {
      "district": null, 
      "name": "Noem, Kristi L.", 
      "sponsored_at": "2014-03-24", 
      "state": "SD", 
      "thomas_id": "02060", 
      "title": "Rep", 
      "withdrawn_at": null
    }, 
    {
      "district": "8", 
      "name": "Nolan, Richard M.", 
      "sponsored_at": "2013-11-19", 
      "state": "MN", 
      "thomas_id": "00867", 
      "title": "Rep", 
      "withdrawn_at": null
    }, 
    {
      "district": null, 
      "name": "Norton, Eleanor Holmes", 
      "sponsored_at": "2013-12-23", 
      "state": "DC", 
      "thomas_id": "00868", 
      "title": "Rep", 
      "withdrawn_at": null
    }, 
    {
      "district": "22", 
      "name": "Olson, Pete", 
      "sponsored_at": "2014-01-13", 
      "state": "TX", 
      "thomas_id": "01955", 
      "title": "Rep", 
      "withdrawn_at": null
    }, 
    {
      "district": "4", 
      "name": "Palazzo, Steven M.", 
      "sponsored_at": "2014-04-29", 
      "state": "MS", 
      "thomas_id": "02035", 
      "title": "Rep", 
      "withdrawn_at": null
    }, 
    {
      "district": "3", 
      "name": "Paulsen, Erik", 
      "sponsored_at": "2013-12-05", 
      "state": "MN", 
      "thomas_id": "01930", 
      "title": "Rep", 
      "withdrawn_at": null
    }, 
    {
      "district": "2", 
      "name": "Pearce, Stevan", 
      "sponsored_at": "2014-05-08", 
      "state": "NM", 
      "thomas_id": "01738", 
      "title": "Rep", 
      "withdrawn_at": null
    }, 
    {
      "district": "52", 
      "name": "Peters, Scott H.", 
      "sponsored_at": "2014-05-08", 
      "state": "CA", 
      "thomas_id": "02113", 
      "title": "Rep", 
      "withdrawn_at": null
    }, 
    {
      "district": "9", 
      "name": "Pittenger, Robert", 
      "sponsored_at": "2014-02-05", 
      "state": "NC", 
      "thomas_id": "02141", 
      "title": "Rep", 
      "withdrawn_at": null
    }, 
    {
      "district": "2", 
      "name": "Pocan, Mark", 
      "sponsored_at": "2013-12-09", 
      "state": "WI", 
      "thomas_id": "02171", 
      "title": "Rep", 
      "withdrawn_at": null
    }, 
    {
      "district": "8", 
      "name": "Posey, Bill", 
      "sponsored_at": "2014-02-05", 
      "state": "FL", 
      "thomas_id": "01915", 
      "title": "Rep", 
      "withdrawn_at": null
    }, 
    {
      "district": "8", 
      "name": "Ribble, Reid J.", 
      "sponsored_at": "2014-02-05", 
      "state": "WI", 
      "thomas_id": "02073", 
      "title": "Rep", 
      "withdrawn_at": null
    }, 
    {
      "district": "1", 
      "name": "Roe, David P.", 
      "sponsored_at": "2014-02-05", 
      "state": "TN", 
      "thomas_id": "01954", 
      "title": "Rep", 
      "withdrawn_at": null
    }, 
    {
      "district": "4", 
      "name": "Rokita, Todd", 
      "sponsored_at": "2014-02-05", 
      "state": "IN", 
      "thomas_id": "02017", 
      "title": "Rep", 
      "withdrawn_at": null
    }, 
    {
      "district": "27", 
      "name": "Ros-Lehtinen, Ileana", 
      "sponsored_at": "2014-03-24", 
      "state": "FL", 
      "thomas_id": "00985", 
      "title": "Rep", 
      "withdrawn_at": null
    }, 
    {
      "district": "6", 
      "name": "Roskam, Peter J.", 
      "sponsored_at": "2014-01-28", 
      "state": "IL", 
      "thomas_id": "01848", 
      "title": "Rep", 
      "withdrawn_at": null
    }, 
    {
      "district": "5", 
      "name": "Salmon, Matt", 
      "sponsored_at": "2014-02-05", 
      "state": "AZ", 
      "thomas_id": "01009", 
      "title": "Rep", 
      "withdrawn_at": null
    }, 
    {
      "district": "18", 
      "name": "Schock, Aaron", 
      "sponsored_at": "2013-12-11", 
      "state": "IL", 
      "thomas_id": "01920", 
      "title": "Rep", 
      "withdrawn_at": null
    }, 
    {
      "district": "8", 
      "name": "Scott, Austin", 
      "sponsored_at": "2014-02-05", 
      "state": "GA", 
      "thomas_id": "02009", 
      "title": "Rep", 
      "withdrawn_at": null
    }, 
    {
      "district": "32", 
      "name": "Sessions, Pete", 
      "sponsored_at": "2014-03-06", 
      "state": "TX", 
      "thomas_id": "01525", 
      "title": "Rep", 
      "withdrawn_at": null
    }, 
    {
      "district": "1", 
      "name": "Shea-Porter, Carol", 
      "sponsored_at": "2014-05-15", 
      "state": "NH", 
      "thomas_id": "01861", 
      "title": "Rep", 
      "withdrawn_at": null
    }, 
    {
      "district": "30", 
      "name": "Sherman, Brad", 
      "sponsored_at": "2014-05-06", 
      "state": "CA", 
      "thomas_id": "01526", 
      "title": "Rep", 
      "withdrawn_at": null
    }, 
    {
      "district": "14", 
      "name": "Speier, Jackie", 
      "sponsored_at": "2014-02-10", 
      "state": "CA", 
      "thomas_id": "01890", 
      "title": "Rep", 
      "withdrawn_at": null
    }, 
    {
      "district": "15", 
      "name": "Stivers, Steve", 
      "sponsored_at": "2014-05-01", 
      "state": "OH", 
      "thomas_id": "02047", 
      "title": "Rep", 
      "withdrawn_at": null
    }, 
    {
      "district": "15", 
      "name": "Swalwell, Eric", 
      "sponsored_at": "2014-01-09", 
      "state": "CA", 
      "thomas_id": "02104", 
      "title": "Rep", 
      "withdrawn_at": null
    }, 
    {
      "district": "1", 
      "name": "Titus, Dina", 
      "sponsored_at": "2014-03-12", 
      "state": "NV", 
      "thomas_id": "01940", 
      "title": "Rep", 
      "withdrawn_at": null
    }, 
    {
      "district": "51", 
      "name": "Vargas, Juan", 
      "sponsored_at": "2014-04-03", 
      "state": "CA", 
      "thomas_id": "02112", 
      "title": "Rep", 
      "withdrawn_at": null
    }, 
    {
      "district": "2", 
      "name": "Wagner, Ann", 
      "sponsored_at": "2014-01-08", 
      "state": "MO", 
      "thomas_id": "02137", 
      "title": "Rep", 
      "withdrawn_at": null
    }, 
    {
      "district": "2", 
      "name": "Walorski, Jackie", 
      "sponsored_at": "2014-04-10", 
      "state": "IN", 
      "thomas_id": "02128", 
      "title": "Rep", 
      "withdrawn_at": null
    }, 
    {
      "district": "14", 
      "name": "Weber, Randy K. Sr.", 
      "sponsored_at": "2014-02-05", 
      "state": "TX", 
      "thomas_id": "02161", 
      "title": "Rep", 
      "withdrawn_at": null
    }, 
    {
      "district": "25", 
      "name": "Williams, Roger", 
      "sponsored_at": "2014-03-04", 
      "state": "TX", 
      "thomas_id": "02165", 
      "title": "Rep", 
      "withdrawn_at": null
    }, 
    {
      "district": "24", 
      "name": "Wilson, Frederica S.", 
      "sponsored_at": "2014-05-09", 
      "state": "FL", 
      "thomas_id": "02004", 
      "title": "Rep", 
      "withdrawn_at": null
    }, 
    {
      "district": "2", 
      "name": "Wilson, Joe", 
      "sponsored_at": "2014-02-05", 
      "state": "SC", 
      "thomas_id": "01688", 
      "title": "Rep", 
      "withdrawn_at": null
    }, 
    {
      "district": "1", 
      "name": "Wittman, Robert J.", 
      "sponsored_at": "2014-02-05", 
      "state": "VA", 
      "thomas_id": "01886", 
      "title": "Rep", 
      "withdrawn_at": null
    }, 
    {
      "district": "10", 
      "name": "Wolf, Frank R.", 
      "sponsored_at": "2014-03-24", 
      "state": "VA", 
      "thomas_id": "01238", 
      "title": "Rep", 
      "withdrawn_at": null
    }, 
    {
      "district": "3", 
      "name": "Yoho, Ted S.", 
      "sponsored_at": "2014-03-26", 
      "state": "FL", 
      "thomas_id": "02115", 
      "title": "Rep", 
      "withdrawn_at": null
    }
  ], 
  "enacted_as": null, 
  "history": {
    "active": true, 
    "active_at": "2014-04-29", 
    "awaiting_signature": false, 
    "enacted": false, 
    "house_passage_result": "pass", 
    "house_passage_result_at": "2014-05-20T18:27:00-04:00", 
    "vetoed": false
  }, 
  "introduced_at": "2013-11-19", 
  "number": "3530", 
  "official_title": "To provide justice for the victims of trafficking.", 
  "popular_title": null, 
  "related_bills": [
    {
      "bill_id": "s1738-113", 
      "reason": "identical", 
      "type": "bill"
    }
  ], 
  "short_title": "Justice for Victims of Trafficking Act of 2014", 
  "sponsor": {
    "district": "2", 
    "name": "Poe, Ted", 
    "state": "TX", 
    "thomas_id": "01802", 
    "title": "Rep", 
    "type": "person"
  }, 
  "status": "PASS_OVER:HOUSE", 
  "status_at": "2014-05-20T18:27:00-04:00", 
  "subjects": [
    "Accounting and auditing", 
    "Administrative law and regulatory procedures", 
    "Administrative remedies", 
    "Adoption and foster care", 
    "Child safety and welfare", 
    "Congressional oversight", 
    "Crime and law enforcement", 
    "Crime victims", 
    "Crimes against children", 
    "Criminal investigation, prosecution, interrogation", 
    "Criminal justice information and records", 
    "Criminal procedure and sentencing", 
    "Department of Health and Human Services", 
    "Department of Justice", 
    "Domestic violence and child abuse", 
    "Evidence and witnesses", 
    "Executive agency funding and structure", 
    "Family services", 
    "Government employee pay, benefits, personnel management", 
    "Government information and archives", 
    "Government studies and investigations", 
    "Government trust funds", 
    "Health programs administration and funding", 
    "Home and outpatient care", 
    "Human trafficking", 
    "Judicial procedure and administration", 
    "Juvenile crime and gang violence", 
    "Law enforcement administration and funding", 
    "Law enforcement officers", 
    "Organized crime", 
    "Pornography", 
    "Sex offenses", 
    "Social work, volunteer service, charitable organizations", 
    "Transportation costs", 
    "Travel and tourism", 
    "Violent crime", 
    "Vocational and technical education"
  ], 
  "subjects_top_term": "Crime and law enforcement", 
  "summary": {
    "as": "Passed House amended", 
    "date": "2014-05-20", 
    "text": "Justice for Victims of Trafficking Act of 2014 - (Sec. 2) Amends the Victims of Crime Act of 1984 to authorize a limitation on obligations to be provided for the Crime Victims Fund for FY2016-FY2020. Specifies that except where such a limitation is made by a continuing resolution, if such a limitation is less than the amount specified for each of those years, all sums deposited in the fund in prior fiscal years shall become available for obligation.\n\n(Sec. 3) Amends the Trafficking Victims Protection Reauthorization Act of 2005 to authorize the Attorney General to make grants to eligible entities to develop, improve, or expand comprehensive domestic child trafficking deterrence programs that assist law enforcement officers, prosecutors, judicial officials, and qualified victims' services organizations in collaborating to rescue and restore the lives of trafficking victims, while investigating and prosecuting offenses involving child human trafficking. Defines an \"eligible entity\" as a state or local government that: (1) has significant criminal activity involving child human trafficking; (2) has demonstrated cooperation between federal, state, local, and tribal law enforcement agencies, prosecutors, and social service providers in addressing child human trafficking; and (3) has developed a workable, multi-disciplinary plan to combat child human trafficking. Authorizes such grants to be used for the establishment or enhancement of:\n\n specialized training programs for law enforcement officers, first responders, health care officials, child welfare officials, juvenile justice personnel, prosecutors, and judicial personnel; dedicated anti-child human trafficking law enforcement units and task forces to investigate child human trafficking offenses and to rescue victims; problem solving court programs for child human trafficking victims; and victims' services programs for victims of child human trafficking. (Sec. 4) Amends the Victims of Child Abuse Act of 1990 to: (1) authorize appropriations for FY2015-FY2019 for the children's advocacy program, multidisciplinary child abuse investigation and prosecution programs, and training and technical assistance to improve the criminal prosecution of child abuse; (2) include human trafficking and the production of child pornography within the definition of \"child abuse\" for purposes of such Act; and (3) authorize grants to develop and implement specialized programs to identify and provide direct services to victims of child pornography.\n\n(Sec. 5) Amends the federal criminal code to allow state and local prosecutors to obtain wiretap warrants in state courts for investigations into human trafficking, child sexual exploitation, and child pornography production.\n\n(Sec. 6) Amends the Crime Control Act of 1990 to require the law enforcement agency that enters a missing children report with the National Crime Information Center to: (1) include a photograph of the child taken within the previous 180 days, and (2) notify the National Center for Missing and Exploited Children of each report received relating to a child reported missing from a foster care family home or childcare institution.\n\n(Sec. 7) Amends the federal criminal code to: (1) apply the prohibition against sex trafficking of minors or of other persons by force, fraud, or coercion to patronizing or soliciting such a person for a commercial sex act, and (2) provide that the government need not prove that the defendant recklessly disregarded the fact that the the victim had not yet attained 18 years of age if the defendant had a reasonable opportunity to observe the victim.\n\n(Sec. 8) Directs the Attorney General to ensure that all task forces and working groups within the Violent Crimes Against Children Program engage in activities to increase the investigative capabilities of law enforcement personnel in the detection, investigation, and prosecution of persons who patronize or solicit children for sex.\n\n(Sec. 9) Modifies the standard for defense to a prosecution for transportation of a minor with intent to engage in criminal sexual activity to require the defendant to show by clear and convincing evidence (currently, by a preponderance of the evidence) that the defendant reasonably believed that the person with whom he or she engaged in the commercial sex act had attained 18 years of age.\n\n(Sec. 10) Requires the Attorney General to audit grants awarded under this Act. Makes a grantee that is found to have an unresolved audit finding ineligible for an allocation of grant funds from the covered grant program during the first 2 fiscal years beginning after the end of the 12-month period from the date on which the final audit report is issued. Requires the Attorney General seek to recoup the costs of the repayment to the Fund from a grantee that was erroneously awarded grant funds. Makes a nonprofit organization that holds money in offshore accounts for the purpose of avoiding paying the tax on unrelated business income ineligible to receive any such grant. Conditions receipt of such a grant by a nonprofit organization on disclosure on its grant application of the compensation of its officers, directors, and trustees.\n\nRestricts the use of grant funds for conferences or lobbying.\n\n(Sec. 11) Amends the federal criminal code to include among the rights of crime victims: (1) the right to be informed in a timely manner of any plea bargain or deferred prosecution agreement, and (2) the right to be informed about all such rights and about victims' services required under the Victims' Rights and Restitution Act of 1990 and to be provided contact information for the Office of the Victims' Rights Ombudsman of the Department of Justice (DOJ). Makes an exception to the requirement that the court of appeals take up and decide an application for a writ of mandamus regarding a motion asserting a victim's right within 72 hours after the petition for such writ has been filed if the litigants, with the approval of the court, have stipulated to a different time period for consideration.\n\n(Sec. 12) Expresses the sense of Congress that: (1) child human trafficking has no place in a civilized society and that persons who commit crimes relating to it should be prosecuted to the fullest extent of the law; (2) the United States, as a leader in monitoring and combating human trafficking throughout the world, must hold all nations to U.S. standards; (3) those who obtain, solicit, or patronize a victim of trafficking for the purpose of engaging in a commercial sex act are committing a human trafficking offense under federal law; and (4) the demand for commercial sex is a primary cause of the human rights violation of human trafficking and the elimination of that violation requires the elimination of that demand."
  }, 
  "titles": [
    {
      "as": "introduced", 
      "is_for_portion": false, 
      "title": "Justice for Victims of Trafficking Act of 2013", 
      "type": "short"
    }, 
    {
      "as": "reported to house", 
      "is_for_portion": false, 
      "title": "Justice for Victims of Trafficking Act of 2014", 
      "type": "short"
    }, 
    {
      "as": "passed house", 
      "is_for_portion": false, 
      "title": "Justice for Victims of Trafficking Act of 2014", 
      "type": "short"
    }, 
    {
      "as": "introduced", 
      "is_for_portion": false, 
      "title": "To provide justice for the victims of trafficking.", 
      "type": "official"
    }
  ], 
  "updated_at": "2015-09-01T10:20:11-04:00", 
  "url": "http://thomas.loc.gov/cgi-bin/bdquery/z?d113:HR3530:@@@L&summ2=m&"
}