{
  "actions": [
    {
      "acted_at": "2013-05-08", 
      "committees": [
        "HSBU"
      ], 
      "references": [], 
      "status": "REFERRED", 
      "text": "Referred to the Committee on the Budget, and in addition to the Committee on Rules, for a period to be subsequently determined by the Speaker, in each case for consideration of such provisions as fall within the jurisdiction of the committee concerned.", 
      "type": "referral"
    }, 
    {
      "acted_at": "2013-05-08", 
      "committees": [
        "HSBU"
      ], 
      "references": [], 
      "text": "Referred to House Budget", 
      "type": "referral"
    }, 
    {
      "acted_at": "2013-05-08", 
      "committees": [
        "HSRU"
      ], 
      "references": [], 
      "text": "Referred to House Rules", 
      "type": "referral"
    }, 
    {
      "acted_at": "2013-06-19", 
      "in_committee": null, 
      "references": [], 
      "text": "Committee Consideration and Mark-up Session Held.", 
      "type": "action"
    }, 
    {
      "acted_at": "2013-06-19", 
      "in_committee": null, 
      "references": [], 
      "status": "REPORTED", 
      "text": "Ordered to be Reported (Amended) by the Yeas and Nays: 22 - 11.", 
      "type": "calendar"
    }, 
    {
      "acted_at": "2013-07-19T15:25:00-04:00", 
      "committees": [
        "HSBU"
      ], 
      "references": [], 
      "text": "Reported (Amended) by the Committee on Budget. H. Rept. 113-161, Part I.", 
      "type": "action"
    }, 
    {
      "acted_at": "2013-07-19T15:26:00-04:00", 
      "committees": [
        "HSRU"
      ], 
      "references": [], 
      "text": "Committee on Rules discharged.", 
      "type": "action"
    }, 
    {
      "acted_at": "2013-07-19T15:26:00-04:00", 
      "calendar": "Union", 
      "number": "116", 
      "references": [], 
      "text": "Placed on the Union Calendar, Calendar No. 116.", 
      "type": "calendar", 
      "under": null
    }, 
    {
      "acted_at": "2014-04-03T16:47:00-04:00", 
      "bill_ids": [
        "hres539-113", 
        "hr1871-113", 
        "hr1872-113"
      ], 
      "committees": [
        "HSRU"
      ], 
      "references": [], 
      "text": "Rules Committee Resolution H. Res. 539 Reported to House. The resolution provides for consideration of H.R. 1874, H.R. 1871, and H.R. 1872. The resolution provides for 1 hour of general debate for each bill. Specified amendments printed in Part B of House Report 113-400 are in order for H.R. 1874. The resolution allows for one motion to recommit with instructions for each bill.", 
      "type": "action"
    }, 
    {
      "acted_at": "2014-04-04T10:56:00-04:00", 
      "bill_ids": [
        "hres539-113"
      ], 
      "references": [
        {
          "reference": "CR H2927-2945", 
          "type": "consideration"
        }
      ], 
      "text": "Considered under the provisions of rule H. Res. 539.", 
      "type": "action"
    }, 
    {
      "acted_at": "2014-04-04T10:57:00-04:00", 
      "bill_ids": [
        "hr1871-113", 
        "hr1872-113"
      ], 
      "references": [], 
      "text": "The resolution provides for consideration of H.R. 1874, H.R. 1871, and H.R. 1872. The resolution provides for 1 hour of general debate for each bill. Specified amendments printed in Part B of House Report 113-400 are in order for H.R. 1874. The resolution allows for one motion to recommit with instructions for each bill.", 
      "type": "action"
    }, 
    {
      "acted_at": "2014-04-04T10:57:00-04:00", 
      "bill_ids": [
        "hres539-113"
      ], 
      "references": [], 
      "text": "House resolved itself into the Committee of the Whole House on the state of the Union pursuant to H. Res. 539 and Rule XVIII.", 
      "type": "action"
    }, 
    {
      "acted_at": "2014-04-04T10:57:00-04:00", 
      "references": [], 
      "text": "The Speaker designated the Honorable Doug Collins to act as Chairman of the Committee.", 
      "type": "action"
    }, 
    {
      "acted_at": "2014-04-04T10:57:00-04:00", 
      "references": [], 
      "text": "GENERAL DEBATE - The Committee of the Whole proceeded with one hour of general debate on H.R. 1874.", 
      "type": "action"
    }, 
    {
      "acted_at": "2014-04-04T12:05:00-04:00", 
      "bill_ids": [
        "hres539-113"
      ], 
      "references": [], 
      "text": "DEBATE - Pursuant to the provisions of H. Res. 539, the Committee of the Whole proceeded with 10 minutes of debate on the Connolly Part B amendment No. 1.", 
      "type": "action"
    }, 
    {
      "acted_at": "2014-04-04T12:12:00-04:00", 
      "references": [], 
      "text": "POSTPONED PROCEEDINGS - At the conclusion of debate on the Connolly amendment No. 1, the Chair put the question on adoption of the amendment and by voice vote announced that the noes had prevailed. Mr. Connolly demanded a recorded vote and the Chair postponed further proceedings on adoption of the amendment until later in the legislative day.", 
      "type": "action"
    }, 
    {
      "acted_at": "2014-04-04T12:13:00-04:00", 
      "bill_ids": [
        "hres539-113"
      ], 
      "references": [], 
      "text": "DEBATE - Pursuant to the provisions of H. Res. 539, the Committee of the Whole proceeded with 10 minutes of debate on the Israel Part B amendment No. 2.", 
      "type": "action"
    }, 
    {
      "acted_at": "2014-04-04T12:18:00-04:00", 
      "references": [], 
      "text": "POSTPONED PROCEEDINGS - At the conclusion of debate on the Israel amendment No. 2, the Chair put the question on adoption of the amendment and by voice vote announced that the noes had prevailed. Mr. Israel demanded a recorded vote and the Chair postponed further proceedings on adoption of the amendment until later in the legislative day.", 
      "type": "action"
    }, 
    {
      "acted_at": "2014-04-04T12:18:00-04:00", 
      "bill_ids": [
        "hres539-113"
      ], 
      "references": [], 
      "text": "DEBATE - Pursuant to the provisions of H. Res. 539, the Committee of the Whole proceeded with 10 minutes of debate on the Cicilline Part B amendment No. 3.", 
      "type": "action"
    }, 
    {
      "acted_at": "2014-04-04T12:25:00-04:00", 
      "references": [], 
      "text": "POSTPONED PROCEEDINGS - At the conclusion of debate on the Cicilline amendment No. 3, the Chair put the question on adoption of the amendment and by voice vote announced that the noes had prevailed. Mr. Cicilline demanded a recorded vote and the Chair postponed further proceedings on adoption of the amendment until later in the legislative day.", 
      "type": "action"
    }, 
    {
      "acted_at": "2014-04-04T12:26:00-04:00", 
      "bill_ids": [
        "hres539-113"
      ], 
      "references": [], 
      "text": "DEBATE - Pursuant to the provisions of H. Res. 539, the Committee of the Whole proceeded with 10 minutes of debate on the Bishop (NY) Part B amendment No. 4.", 
      "type": "action"
    }, 
    {
      "acted_at": "2014-04-04T12:30:00-04:00", 
      "bill_ids": [
        "hres539-113"
      ], 
      "references": [], 
      "text": "DEBATE - Pursuant to the provisions of H. Res. 539, the Committee of the Whole proceeded with 10 minutes of debate on the Jackson Lee (TX) Part B amendment No. 5.", 
      "type": "action"
    }, 
    {
      "acted_at": "2014-04-04T12:37:00-04:00", 
      "references": [], 
      "text": "POSTPONED PROCEEDINGS - At the conclusion of debate on the Jackson Lee (TX) amendment No. 5, the Chair put the question on adoption of the amendment and by voice vote announced that the noes had prevailed. Ms. Jackson Lee (TX) demanded a recorded vote and the Chair postponed further proceedings on adoption of the amendment until later in the legislative day.", 
      "type": "action"
    }, 
    {
      "acted_at": "2014-04-04T12:38:00-04:00", 
      "references": [], 
      "text": "UNFINISHED BUSINESS - The Chair announced that the unfinished business was the question on adoption of amendments which had been debated earlier and on which further proceedings had been postponed.", 
      "type": "action"
    }, 
    {
      "acted_at": "2014-04-04T13:18:00-04:00", 
      "references": [], 
      "text": "The House rose from the Committee of the Whole House on the state of the Union to report H.R. 1874.", 
      "type": "action"
    }, 
    {
      "acted_at": "2014-04-04T13:19:00-04:00", 
      "references": [
        {
          "reference": "CR H2943", 
          "type": "consideration"
        }
      ], 
      "text": "The previous question was ordered pursuant to the rule.", 
      "type": "action"
    }, 
    {
      "acted_at": "2014-04-04T13:19:00-04:00", 
      "references": [
        {
          "reference": "CR H2935-2936", 
          "type": "text of committee amendment"
        }
      ], 
      "text": "The House adopted the amendment as agreed to by the Committee of the Whole House on the state of the Union.", 
      "type": "action"
    }, 
    {
      "acted_at": "2014-04-04T13:20:00-04:00", 
      "committees": [
        "HSBU"
      ], 
      "references": [
        {
          "reference": "CR H2943-2944", 
          "type": "consideration"
        }, 
        {
          "reference": "CR H2943", 
          "type": "text"
        }
      ], 
      "text": "Ms. Kuster moved to recommit with instructions to the Committee on the Budget.", 
      "type": "action"
    }, 
    {
      "acted_at": "2014-04-04T13:21:00-04:00", 
      "references": [], 
      "text": "Floor summary: DEBATE - The House proceeeded with 10 minutes of debate on the Kuster motion to recommit with instructions. The instructions contained in the motion seek to require the bill to be reported back to the House with an amendment to require any dynamic score under the bill to include impacts on job creation and economic growth of any investment in education, transportation and infrastructure. It also allows appropriations bills to benefit from dynamic scoring under the bill.", 
      "type": "action"
    }, 
    {
      "acted_at": "2014-04-04T13:26:00-04:00", 
      "references": [
        {
          "reference": "CR H2944", 
          "type": "consideration"
        }
      ], 
      "text": "The previous question on the motion to recommit with instructions was ordered without objection.", 
      "type": "action"
    }, 
    {
      "acted_at": "2014-04-04T13:33:00-04:00", 
      "references": [], 
      "text": "On motion to recommit with instructions Failed by recorded vote: 187 - 218 (Roll no. 163).", 
      "type": "action"
    }, 
    {
      "acted_at": "2014-04-04T13:42:00-04:00", 
      "how": "roll", 
      "references": [], 
      "result": "pass", 
      "roll": "164", 
      "status": "PASS_OVER:HOUSE", 
      "suspension": null, 
      "text": "On passage Passed by recorded vote: 224 - 182 (Roll no. 164).", 
      "type": "vote", 
      "vote_type": "vote", 
      "where": "h"
    }, 
    {
      "acted_at": "2014-04-04T13:42:00-04:00", 
      "references": [], 
      "text": "Motion to reconsider laid on the table Agreed to without objection.", 
      "type": "action"
    }, 
    {
      "acted_at": "2014-04-07", 
      "committees": [
        "SSBU"
      ], 
      "references": [], 
      "text": "Received in the Senate and Read twice and referred to the Committee on the Budget.", 
      "type": "referral"
    }
  ], 
  "amendments": [
    {
      "amendment_id": "hamdt605-113", 
      "amendment_type": "hamdt", 
      "chamber": "h", 
      "number": "605"
    }, 
    {
      "amendment_id": "hamdt606-113", 
      "amendment_type": "hamdt", 
      "chamber": "h", 
      "number": "606"
    }, 
    {
      "amendment_id": "hamdt607-113", 
      "amendment_type": "hamdt", 
      "chamber": "h", 
      "number": "607"
    }, 
    {
      "amendment_id": "hamdt608-113", 
      "amendment_type": "hamdt", 
      "chamber": "h", 
      "number": "608"
    }, 
    {
      "amendment_id": "hamdt609-113", 
      "amendment_type": "hamdt", 
      "chamber": "h", 
      "number": "609"
    }
  ], 
  "bill_id": "hr1874-113", 
  "bill_type": "hr", 
  "by_request": false, 
  "committees": [
    {
      "activity": [
        "referral", 
        "markup", 
        "reporting", 
        "in committee"
      ], 
      "committee": "House Budget", 
      "committee_id": "HSBU"
    }, 
    {
      "activity": [
        "referral", 
        "discharged", 
        "in committee"
      ], 
      "committee": "House Rules", 
      "committee_id": "HSRU"
    }, 
    {
      "activity": [
        "referral"
      ], 
      "committee": "Senate Budget", 
      "committee_id": "SSBU"
    }
  ], 
  "congress": "113", 
  "cosponsors": [
    {
      "district": "11", 
      "name": "Barletta, Lou", 
      "sponsored_at": "2013-07-17", 
      "state": "PA", 
      "thomas_id": "02054", 
      "title": "Rep", 
      "withdrawn_at": null
    }, 
    {
      "district": "6", 
      "name": "Barr, Andy", 
      "sponsored_at": "2013-05-08", 
      "state": "KY", 
      "thomas_id": "02131", 
      "title": "Rep", 
      "withdrawn_at": null
    }, 
    {
      "district": "1", 
      "name": "Bishop, Rob", 
      "sponsored_at": "2013-05-08", 
      "state": "UT", 
      "thomas_id": "01753", 
      "title": "Rep", 
      "withdrawn_at": null
    }, 
    {
      "district": "6", 
      "name": "Black, Diane", 
      "sponsored_at": "2013-05-08", 
      "state": "TN", 
      "thomas_id": "02063", 
      "title": "Rep", 
      "withdrawn_at": null
    }, 
    {
      "district": "8", 
      "name": "Bucshon, Larry", 
      "sponsored_at": "2013-05-13", 
      "state": "IN", 
      "thomas_id": "02018", 
      "title": "Rep", 
      "withdrawn_at": null
    }, 
    {
      "district": "3", 
      "name": "Chaffetz, Jason", 
      "sponsored_at": "2013-05-08", 
      "state": "UT", 
      "thomas_id": "01956", 
      "title": "Rep", 
      "withdrawn_at": null
    }, 
    {
      "district": "9", 
      "name": "Collins, Doug", 
      "sponsored_at": "2013-05-08", 
      "state": "GA", 
      "thomas_id": "02121", 
      "title": "Rep", 
      "withdrawn_at": null
    }, 
    {
      "district": "4", 
      "name": "Cotton, Tom", 
      "sponsored_at": "2013-05-08", 
      "state": "AR", 
      "thomas_id": "02098", 
      "title": "Rep", 
      "withdrawn_at": null
    }, 
    {
      "district": "4", 
      "name": "Forbes, J. Randy", 
      "sponsored_at": "2013-05-16", 
      "state": "VA", 
      "thomas_id": "01683", 
      "title": "Rep", 
      "withdrawn_at": null
    }, 
    {
      "district": "1", 
      "name": "Fortenberry, Jeff", 
      "sponsored_at": "2013-05-08", 
      "state": "NE", 
      "thomas_id": "01793", 
      "title": "Rep", 
      "withdrawn_at": null
    }, 
    {
      "district": "8", 
      "name": "Franks, Trent", 
      "sponsored_at": "2013-05-08", 
      "state": "AZ", 
      "thomas_id": "01707", 
      "title": "Rep", 
      "withdrawn_at": null
    }, 
    {
      "district": "5", 
      "name": "Garrett, Scott", 
      "sponsored_at": "2013-05-08", 
      "state": "NJ", 
      "thomas_id": "01737", 
      "title": "Rep", 
      "withdrawn_at": null
    }, 
    {
      "district": "4", 
      "name": "Gosar, Paul A.", 
      "sponsored_at": "2013-05-08", 
      "state": "AZ", 
      "thomas_id": "01992", 
      "title": "Rep", 
      "withdrawn_at": null
    }, 
    {
      "district": "14", 
      "name": "Graves, Tom", 
      "sponsored_at": "2013-05-08", 
      "state": "GA", 
      "thomas_id": "01979", 
      "title": "Rep", 
      "withdrawn_at": null
    }, 
    {
      "district": "3", 
      "name": "Harper, Gregg", 
      "sponsored_at": "2013-06-27", 
      "state": "MS", 
      "thomas_id": "01933", 
      "title": "Rep", 
      "withdrawn_at": null
    }, 
    {
      "district": "4", 
      "name": "Hartzler, Vicky", 
      "sponsored_at": "2013-06-05", 
      "state": "MO", 
      "thomas_id": "02032", 
      "title": "Rep", 
      "withdrawn_at": null
    }, 
    {
      "district": "5", 
      "name": "Hensarling, Jeb", 
      "sponsored_at": "2013-05-08", 
      "state": "TX", 
      "thomas_id": "01749", 
      "title": "Rep", 
      "withdrawn_at": null
    }, 
    {
      "district": "2", 
      "name": "Huizenga, Bill", 
      "sponsored_at": "2013-06-27", 
      "state": "MI", 
      "thomas_id": "02028", 
      "title": "Rep", 
      "withdrawn_at": null
    }, 
    {
      "district": "5", 
      "name": "Hurt, Robert", 
      "sponsored_at": "2013-06-06", 
      "state": "VA", 
      "thomas_id": "02069", 
      "title": "Rep", 
      "withdrawn_at": null
    }, 
    {
      "district": "6", 
      "name": "Johnson, Bill", 
      "sponsored_at": "2013-05-08", 
      "state": "OH", 
      "thomas_id": "02046", 
      "title": "Rep", 
      "withdrawn_at": null
    }, 
    {
      "district": "4", 
      "name": "Jordan, Jim", 
      "sponsored_at": "2013-05-08", 
      "state": "OH", 
      "thomas_id": "01868", 
      "title": "Rep", 
      "withdrawn_at": null
    }, 
    {
      "district": "1", 
      "name": "Kingston, Jack", 
      "sponsored_at": "2013-05-15", 
      "state": "GA", 
      "thomas_id": "00636", 
      "title": "Rep", 
      "withdrawn_at": null
    }, 
    {
      "district": "16", 
      "name": "Kinzinger, Adam", 
      "sponsored_at": "2013-07-17", 
      "state": "IL", 
      "thomas_id": "02014", 
      "title": "Rep", 
      "withdrawn_at": null
    }, 
    {
      "district": "2", 
      "name": "Kline, John", 
      "sponsored_at": "2013-05-15", 
      "state": "MN", 
      "thomas_id": "01733", 
      "title": "Rep", 
      "withdrawn_at": null
    }, 
    {
      "district": "24", 
      "name": "Marchant, Kenny", 
      "sponsored_at": "2013-05-08", 
      "state": "TX", 
      "thomas_id": "01806", 
      "title": "Rep", 
      "withdrawn_at": null
    }, 
    {
      "district": "4", 
      "name": "McClintock, Tom", 
      "sponsored_at": "2013-05-20", 
      "state": "CA", 
      "thomas_id": "01908", 
      "title": "Rep", 
      "withdrawn_at": null
    }, 
    {
      "district": "11", 
      "name": "Meadows, Mark", 
      "sponsored_at": "2013-07-10", 
      "state": "NC", 
      "thomas_id": "02142", 
      "title": "Rep", 
      "withdrawn_at": null
    }, 
    {
      "district": "6", 
      "name": "Messer, Luke", 
      "sponsored_at": "2013-06-14", 
      "state": "IN", 
      "thomas_id": "02130", 
      "title": "Rep", 
      "withdrawn_at": null
    }, 
    {
      "district": "5", 
      "name": "Mulvaney, Mick", 
      "sponsored_at": "2013-05-08", 
      "state": "SC", 
      "thomas_id": "02059", 
      "title": "Rep", 
      "withdrawn_at": null
    }, 
    {
      "district": "11", 
      "name": "Nugent, Richard B.", 
      "sponsored_at": "2013-05-09", 
      "state": "FL", 
      "thomas_id": "02001", 
      "title": "Rep", 
      "withdrawn_at": null
    }, 
    {
      "district": "3", 
      "name": "Paulsen, Erik", 
      "sponsored_at": "2013-05-09", 
      "state": "MN", 
      "thomas_id": "01930", 
      "title": "Rep", 
      "withdrawn_at": null
    }, 
    {
      "district": "2", 
      "name": "Pearce, Stevan", 
      "sponsored_at": "2013-05-15", 
      "state": "NM", 
      "thomas_id": "01738", 
      "title": "Rep", 
      "withdrawn_at": null
    }, 
    {
      "district": "9", 
      "name": "Pittenger, Robert", 
      "sponsored_at": "2013-05-08", 
      "state": "NC", 
      "thomas_id": "02141", 
      "title": "Rep", 
      "withdrawn_at": null
    }, 
    {
      "district": "19", 
      "name": "Radel, Trey", 
      "sponsored_at": "2013-05-08", 
      "state": "FL", 
      "thomas_id": "02118", 
      "title": "Rep", 
      "withdrawn_at": null
    }, 
    {
      "district": "23", 
      "name": "Reed, Tom", 
      "sponsored_at": "2013-05-08", 
      "state": "NY", 
      "thomas_id": "01982", 
      "title": "Rep", 
      "withdrawn_at": null
    }, 
    {
      "district": "8", 
      "name": "Ribble, Reid J.", 
      "sponsored_at": "2013-05-08", 
      "state": "WI", 
      "thomas_id": "02073", 
      "title": "Rep", 
      "withdrawn_at": null
    }, 
    {
      "district": "4", 
      "name": "Rokita, Todd", 
      "sponsored_at": "2013-06-17", 
      "state": "IN", 
      "thomas_id": "02017", 
      "title": "Rep", 
      "withdrawn_at": null
    }, 
    {
      "district": "15", 
      "name": "Ross, Dennis A.", 
      "sponsored_at": "2013-05-08", 
      "state": "FL", 
      "thomas_id": "02003", 
      "title": "Rep", 
      "withdrawn_at": null
    }, 
    {
      "district": "1", 
      "name": "Ryan, Paul", 
      "sponsored_at": "2013-05-08", 
      "state": "WI", 
      "thomas_id": "01560", 
      "title": "Rep", 
      "withdrawn_at": null
    }, 
    {
      "district": "1", 
      "name": "Scalise, Steve", 
      "sponsored_at": "2013-05-08", 
      "state": "LA", 
      "thomas_id": "01892", 
      "title": "Rep", 
      "withdrawn_at": null
    }, 
    {
      "district": "18", 
      "name": "Schock, Aaron", 
      "sponsored_at": "2013-07-08", 
      "state": "IL", 
      "thomas_id": "01920", 
      "title": "Rep", 
      "withdrawn_at": null
    }, 
    {
      "district": "8", 
      "name": "Scott, Austin", 
      "sponsored_at": "2013-05-08", 
      "state": "GA", 
      "thomas_id": "02009", 
      "title": "Rep", 
      "withdrawn_at": null
    }, 
    {
      "district": "2", 
      "name": "Terry, Lee", 
      "sponsored_at": "2013-05-08", 
      "state": "NE", 
      "thomas_id": "01566", 
      "title": "Rep", 
      "withdrawn_at": null
    }, 
    {
      "district": "12", 
      "name": "Tiberi, Patrick J.", 
      "sponsored_at": "2013-05-15", 
      "state": "OH", 
      "thomas_id": "01664", 
      "title": "Rep", 
      "withdrawn_at": null
    }, 
    {
      "district": "3", 
      "name": "Westmoreland, Lynn A.", 
      "sponsored_at": "2013-05-08", 
      "state": "GA", 
      "thomas_id": "01779", 
      "title": "Rep", 
      "withdrawn_at": null
    }, 
    {
      "district": "2", 
      "name": "Wilson, Joe", 
      "sponsored_at": "2013-05-08", 
      "state": "SC", 
      "thomas_id": "01688", 
      "title": "Rep", 
      "withdrawn_at": null
    }, 
    {
      "district": "7", 
      "name": "Woodall, Rob", 
      "sponsored_at": "2013-05-08", 
      "state": "GA", 
      "thomas_id": "02008", 
      "title": "Rep", 
      "withdrawn_at": null
    }, 
    {
      "district": "3", 
      "name": "Yoder, Kevin", 
      "sponsored_at": "2013-05-08", 
      "state": "KS", 
      "thomas_id": "02021", 
      "title": "Rep", 
      "withdrawn_at": null
    }, 
    {
      "district": "9", 
      "name": "Young, Todd C.", 
      "sponsored_at": "2013-07-08", 
      "state": "IN", 
      "thomas_id": "02019", 
      "title": "Rep", 
      "withdrawn_at": null
    }
  ], 
  "enacted_as": null, 
  "history": {
    "active": true, 
    "active_at": "2013-06-19", 
    "awaiting_signature": false, 
    "enacted": false, 
    "house_passage_result": "pass", 
    "house_passage_result_at": "2014-04-04T13:42:00-04:00", 
    "vetoed": false
  }, 
  "introduced_at": "2013-05-08", 
  "number": "1874", 
  "official_title": "To amend the Congressional Budget Act of 1974 to provide for macroeconomic analysis of the impact of legislation.", 
  "popular_title": null, 
  "related_bills": [
    {
      "bill_id": "hres539-113", 
      "reason": "related", 
      "type": "bill"
    }, 
    {
      "bill_id": "hres539-113", 
      "reason": "rule", 
      "type": "bill"
    }, 
    {
      "bill_id": "s184-113", 
      "reason": "related", 
      "type": "bill"
    }, 
    {
      "bill_id": "s2371-113", 
      "reason": "related", 
      "type": "bill"
    }
  ], 
  "short_title": "Pro-Growth Budgeting Act of 2014", 
  "sponsor": {
    "district": "6", 
    "name": "Price, Tom", 
    "state": "GA", 
    "thomas_id": "01778", 
    "title": "Rep", 
    "type": "person"
  }, 
  "status": "PASS_OVER:HOUSE", 
  "status_at": "2014-04-04T13:42:00-04:00", 
  "subjects": [
    "Budget process", 
    "Congressional oversight", 
    "Economic performance and conditions", 
    "Economic theory", 
    "Economics and public finance", 
    "Government studies and investigations", 
    "Legislative rules and procedure"
  ], 
  "subjects_top_term": "Economics and public finance", 
  "summary": {
    "as": "Passed House amended", 
    "date": "2014-04-04", 
    "text": "Pro-Growth Budgeting Act of 2014 - Amends the Congressional Budget Act of 1974 (CBA) to require the Congressional Budget Office (CBO) to prepare for each major bill or resolution reported by any congressional committee (except the congressional appropriations committees), as a supplement to CBO cost estimates, a macroeconomic impact analysis of the budgetary effects of such legislation for the 10-fiscal year period beginning with the first fiscal year for which such estimate was prepared and each of the next three 10-fiscal year periods.\n\nDefines \"major bill or resolution\" as any bill or resolution whose budgetary effects, for any fiscal year in the period for which a CBO cost estimate is prepared, is estimated to be greater than .25% of the current projected U.S. gross domestic product (GDP) for that fiscal year.\n\nRequires the analysis to describe: (1) the potential economic impact of the bill or resolution on major economic variables, including real GDP, business investment, the capital stock, employment, interest rates, and labor supply; and (2) the potential fiscal effects of the measure, including any estimates of revenue increases or decreases resulting from changes in GDP.\n\nRequires the analysis (or a technical appendix to it) to specify the economic and econometric models used, sources of data, relevant data transformations, as well as any explanation necessary to make the models comprehensible to academic and public policy analysts. Requires the CBO, five fiscal years after the enactment of any major bill or joint resolution for which it prepared a macroeconomic impact analysis, to report to the congressional budget committees on the accuracy of the original analysis."
  }, 
  "titles": [
    {
      "as": "introduced", 
      "is_for_portion": false, 
      "title": "Pro-Growth Budgeting Act of 2013", 
      "type": "short"
    }, 
    {
      "as": "reported to house", 
      "is_for_portion": false, 
      "title": "Pro-Growth Budgeting Act of 2013", 
      "type": "short"
    }, 
    {
      "as": "passed house", 
      "is_for_portion": false, 
      "title": "Pro-Growth Budgeting Act of 2014", 
      "type": "short"
    }, 
    {
      "as": "introduced", 
      "is_for_portion": false, 
      "title": "To amend the Congressional Budget Act of 1974 to provide for macroeconomic analysis of the impact of legislation.", 
      "type": "official"
    }
  ], 
  "updated_at": "2015-09-01T10:19:31-04:00", 
  "url": "http://thomas.loc.gov/cgi-bin/bdquery/z?d113:HR1874:@@@L&summ2=m&"
}